{"name":"Gwen","winRate":51.84,"pickRate":54.86,"banRate":1.1,"stats":[{"name":"goldPerMin","stats":609.11,"rank":1,"total":39},{"name":"killsPerGame","stats":5.63,"rank":7,"total":39},{"name":"deathsPerGame","stats":4.95,"rank":16,"total":39},{"name":"assistsPerGame","stats":5.54,"rank":29,"total":39},{"name":"farmPerGame","stats":89.31,"rank":3,"total":39},{"name":"damagePerGame","stats":53159.31,"rank":10,"total":39},{"name":"healingPerGame","stats":7453.43,"rank":35,"total":39},{"name":"kda","stats":2.26,"rank":21,"total":39}],"roles":[{"key":"Carry","winRate":52.13,"pickRate":94.41},{"key":"Jungler","winRate":49.6,"pickRate":4.9},{"key":"Captain","winRate":27.1,"pickRate":0.69}],"durations":[{"key":"10","winRate":48.58,"pickRate":3.43},{"key":"20","winRate":51.27,"pickRate":39.01},{"key":"30","winRate":52.43,"pickRate":52.19},{"key":"40","winRate":52.19,"pickRate":5.33},{"key":"50","winRate":66.67,"pickRate":0.04}],"playingAgainst":[{"key":"Adagio","winRate":53,"pickRate":8.97},{"key":"Alpha","winRate":52.21,"pickRate":7.77},{"key":"Ardan","winRate":51.71,"pickRate":25.9},{"key":"Baptiste","winRate":55.13,"pickRate":8.4},{"key":"Baron","winRate":51.78,"pickRate":14.02},{"key":"Blackfeather","winRate":54.77,"pickRate":14.05},{"key":"Catherine","winRate":50.11,"pickRate":17.69},{"key":"Celeste","winRate":48.11,"pickRate":25.32},{"key":"Churnwalker","winRate":52.89,"pickRate":3.48},{"key":"Flicker","winRate":51.16,"pickRate":5.85},{"key":"Fortress","winRate":47.49,"pickRate":11.6},{"key":"Glaive","winRate":55.14,"pickRate":11.73},{"key":"Grace","winRate":47.55,"pickRate":15.85},{"key":"Grumpjaw","winRate":50.33,"pickRate":5.94},{"key":"Idris","winRate":50.61,"pickRate":23.76},{"key":"Joule","winRate":51.49,"pickRate":11.53},{"key":"Kestrel","winRate":54.6,"pickRate":18.94},{"key":"Koshka","winRate":51.16,"pickRate":14.46},{"key":"Krul","winRate":49.81,"pickRate":12.03},{"key":"Lance","winRate":59.09,"pickRate":5.67},{"key":"Lorelai","winRate":52.37,"pickRate":2.73},{"key":"Lyra","winRate":49.49,"pickRate":15.32},{"key":"Malene","winRate":50.43,"pickRate":12},{"key":"Ozo","winRate":53.86,"pickRate":3.78},{"key":"Petal","winRate":50.77,"pickRate":6.75},{"key":"Phinn","winRate":52.72,"pickRate":3.69},{"key":"Reim","winRate":57.39,"pickRate":3.77},{"key":"Reza","winRate":51.3,"pickRate":10.23},{"key":"Ringo","winRate":54.06,"pickRate":25.3},{"key":"Rona","winRate":48.35,"pickRate":20.18},{"key":"SAW","winRate":57.36,"pickRate":9.86},{"key":"Samuel","winRate":55.17,"pickRate":14.24},{"key":"Skaarf","winRate":48.68,"pickRate":18.94},{"key":"Skye","winRate":54.35,"pickRate":12.35},{"key":"Taka","winRate":59.57,"pickRate":6.4},{"key":"Tony","winRate":49.59,"pickRate":14.35},{"key":"Varya","winRate":53.55,"pickRate":15.4},{"key":"Vox","winRate":52.77,"pickRate":41.75}],"playingWith":[{"key":"Adagio","winRate":51.29,"pickRate":7.3},{"key":"Alpha","winRate":48.75,"pickRate":7.27},{"key":"Ardan","winRate":52.65,"pickRate":25.07},{"key":"Baptiste","winRate":50.23,"pickRate":6.9},{"key":"Baron","winRate":51.87,"pickRate":9.54},{"key":"Blackfeather","winRate":47.34,"pickRate":10.58},{"key":"Catherine","winRate":53.48,"pickRate":18.26},{"key":"Celeste","winRate":55.6,"pickRate":22.17},{"key":"Churnwalker","winRate":49.63,"pickRate":3.49},{"key":"Flicker","winRate":48.87,"pickRate":6.01},{"key":"Fortress","winRate":56.82,"pickRate":11.59},{"key":"Glaive","winRate":48.71,"pickRate":8.77},{"key":"Grace","winRate":54.91,"pickRate":13.46},{"key":"Grumpjaw","winRate":45.6,"pickRate":4.86},{"key":"Idris","winRate":54.56,"pickRate":18.1},{"key":"Joule","winRate":51.45,"pickRate":8.95},{"key":"Kestrel","winRate":47.18,"pickRate":12.51},{"key":"Koshka","winRate":52.21,"pickRate":14.83},{"key":"Krul","winRate":53.97,"pickRate":9.95},{"key":"Lance","winRate":45.39,"pickRate":5.34},{"key":"Lorelai","winRate":54.36,"pickRate":2.53},{"key":"Lyra","winRate":53.88,"pickRate":14.18},{"key":"Malene","winRate":55.49,"pickRate":10.57},{"key":"Ozo","winRate":49.7,"pickRate":4.32},{"key":"Petal","winRate":53.85,"pickRate":6.05},{"key":"Phinn","winRate":49.84,"pickRate":4.12},{"key":"Reim","winRate":50.28,"pickRate":4.61},{"key":"Reza","winRate":51.43,"pickRate":10.18},{"key":"Ringo","winRate":47.22,"pickRate":10.26},{"key":"Rona","winRate":54.78,"pickRate":14.36},{"key":"SAW","winRate":48.48,"pickRate":5.32},{"key":"Samuel","winRate":52.18,"pickRate":12.94},{"key":"Skaarf","winRate":55.25,"pickRate":16.36},{"key":"Skye","winRate":46.87,"pickRate":8.59},{"key":"Taka","winRate":42.42,"pickRate":5.99},{"key":"Tony","winRate":52.42,"pickRate":11.36},{"key":"Varya","winRate":52.19,"pickRate":13.19},{"key":"Vox","winRate":49.28,"pickRate":20.13}],"builds":[{"key":"TB,SB,BP,AE","winRate":56.66,"pickRate":12.35,"variants":["TB,SB,BP,AE","TB,SB,BP,AE,HC","TB,SB,BP,AE,JB","TB,SB,BP,AE,JB,MJ","TB,SB,BP,AE,JB,MJ,PS","TB,SB,BP,AE,JB,BS","TB,SB,BP,AE,JB,PS","TB,SB,BP,AE,JB,SM","TB,SB,BP,AE,HC,PS","TB,SB,BP,AE,MJ","TB,SB,BP,AE,JB,MJ,JB","TB,SB,BP,AE,SS,JB","TB,SB,BP,AE,BS,WT","TB,SB,BP,AE,JB,WT","TB,SB,BP,AE,SB,JB","TB,SB,BP,AE,AP","TB,SB,BP,AE,JB,BS,BS,BS","TB,SB,BP,AE,JB,MJ,BS","TB,SB,BP,AE,JB,MJ,SH","TB,SB,BP,AE,MJ,HC","TB,SB,BP,AE,JB,TT","TB,SB,BP,AE,PS","TB,SB,BP,AE,TT,JB","TB,SB,BP,AE,BS","TB,SB,BP,AE,SM","TB,SB,BP,AE,PS,HC","TB,SB,BP,AE,TT,TT","TB,SB,BP,AE,HC,JB","TB,SB,BP,AE,MJ,BS","TB,SB,BP,AE,TT","TB,SB,BP,AE,MJ,JB","TB,SB,BP,AE,MJ,WT","TB,SB,BP,AE,BS,HC","TB,SB,BP,AE,MJ,JB,BS","TB,SB,BP,AE,JB,MJ,TT","TB,SB,BP,AE,JB,SS,HC","TB,SB,BP,AE,TT,WT","TB,SB,BP,AE,HC,MJ,HC","TB,SB,BP,AE,JB,AP,PS","TB,SB,BP,AE,JB,BP","TB,SB,BP,AE,JB,FR","TB,SB,BP,AE,JB,MJ,MJ","TB,SB,BP,AE,PS,JB","TB,SB,BP,AE,HC,SS","TB,SB,BP,AE,JB,MJ,BS,CB","TB,SB,BP,AE,JB,SB","TB,SB,BP,AE,SC","TB,SB,BP,AE,WT","TB,SB,BP,AE,WT,MJ","TB,SB,BP,AE,JB,MJ,SB","TB,SB,BP,AE,JB,MJ,WT","TB,SB,BP,AE,JB,JB","TB,SB,BP,AE,WT,SS","TB,SB,BP,AE,HC,MJ","TB,SB,BP,AE,JB,MJ,AP,AP,AP,AP","TB,SB,BP,AE,JB,PS,HC","TB,SB,BP,AE,JB,SM,BS","TB,SB,BP,AE,PS,JB,BS","TB,SB,BP,AE,WT,SB,MJ,SB","TB,SB,BP,AE,HC,TT","TB,SB,BP,AE,JB,PS,MJ","TB,SB,BP,AE,BS,JB","TB,SB,BP,AE,HC,MJ,BS","TB,SB,BP,AE,JB,AP","TB,SB,BP,AE,HC,BS","TB,SB,BP,AE,JB,MJ,SM","TB,SB,BP,AE,WT,TT","TB,SB,BP,AE,AP,JB","TB,SB,BP,AE,HC,AP","TB,SB,BP,AE,JB,TB","TB,SB,BP,AE,JB,MJ,HC","TB,SB,BP,AE,JB,MJ,SH,PS","TB,SB,BP,AE,SH,WT","TB,SB,BP,AE,JB,SH","TB,SB,BP,AE,JB,SS","TB,SB,BP,AE,TT,HC","TB,SB,BP,AE,MJ,HC,JB","TB,SB,BP,AE,HC,SB","TB,SB,BP,AE,JB,AE","TB,SB,BP,AE,JB,TB,TB","TB,SB,BP,AE,MJ,HC,BS","TB,SB,BP,AE,JB,PS,TT","TB,SB,BP,AE,JB,BS,WT","TB,SB,BP,AE,JB,MJ,AP,PS","TB,SB,BP,AE,TT,JB,HC"],"items":["Tension Bow","Sorrowblade","Breaking Point","Aegis"]},{"key":"TB,SB,AE,BP","winRate":57,"pickRate":1.94,"variants":["TB,SB,AE,BP","TB,SB,AE,BP,HC","TB,SB,AE,BP,JB","TB,SB,AE,BP,JB,MJ","TB,SB,AE,BP,JB,AP","TB,SB,AE,BP,MJ","TB,SB,AE,BP,MJ,JB","TB,SB,AE,BP,MJ,HC","TB,SB,AE,BP,WT,MJ","TB,SB,AE,BP,JB,SM","TB,SB,AE,BP,BS","TB,SB,AE,BP,BP","TB,SB,AE,BP,WT,SB","TB,SB,AE,BP,AP","TB,SB,AE,BP,WT","TB,SB,AE,BP,JB,BS","TB,SB,AE,BP,JB,TT","TB,SB,AE,BP,PS","TB,SB,AE,BP,WT,SH","TB,SB,AE,BP,JB,PS","TB,SB,AE,BP,JB,MJ,SB","TB,SB,AE,BP,SB","TB,SB,AE,BP,JB,MJ,PS","TB,SB,AE,BP,TT","TB,SB,AE,BP,PS,HC","TB,SB,AE,BP,BS,JB","TB,SB,AE,BP,MJ,WT","TB,SB,AE,BP,SH,JB","TB,SB,AE,BP,HC,MJ","TB,SB,AE,BP,HC,SB","TB,SB,AE,BP,JB,AE,HC","TB,SB,AE,BP,JB,MJ,SM","TB,SB,AE,BP,SS,JB","TB,SB,AE,BP,JB,JB","TB,SB,AE,BP,PS,JB","TB,SB,AE,BP,JB,MJ,BS"],"items":["Tension Bow","Sorrowblade","Aegis","Breaking Point"]},{"key":"TB,SB,BP,**","winRate":65.38,"pickRate":1.68,"variants":["TB,SB,BP,HC,AE","TB,SB,BP,HC,AE,MJ","TB,SB,BP,HC","TB,SB,BP,HC,MJ","TB,SB,BP,HC,SS,BS","TB,SB,BP,HC,MJ,AE","TB,SB,BP,HC,AE,PS","TB,SB,BP,HC,AE,SH","TB,SB,BP,HC,BS,AE","TB,SB,BP,HC,SS,AE","TB,SB,BP,HC,AE,SB","TB,SB,BP,HC,AE,AP","TB,SB,BP,HC,AE,MJ,WT","TB,SB,BP,HC,PS","TB,SB,BP,HC,SS,MJ","TB,SB,BP,HC,MJ,AE,SM","TB,SB,BP,HC,AE,BS","TB,SB,BP,HC,AE,TB,TT","TB,SB,BP,HC,TT","TB,SB,BP,HC,AE,JB","TB,SB,BP,HC,SH","TB,SB,BP,HC,AE,TB","TB,SB,BP,HC,AE,MJ,BS","TB,SB,BP,JB","TB,SB,BP,JB,AE","TB,SB,BP,JB,MJ,AE,TT","TB,SB,BP,JB,MJ,AE","TB,SB,BP,JB,JB","TB,SB,BP,JB,MJ","TB,SB,BP,JB,TT,PS","TB,SB,BP,JB,AE,BS","TB,SB,BP,JB,SH","TB,SB,BP,JB,SM,AE","TB,SB,BP,JB,TT","TB,SB,BP,JB,AE,MJ","TB,SB,BP,JB,MJ,SS","TB,SB,BP,JB,AE,MJ,PS","TB,SB,BP,JB,AE,MJ,JB","TB,SB,BP,JB,BS","TB,SB,BP,JB,SM","TB,SB,BP,JB,BS,PS","TB,SB,BP,JB,PS,MJ","TB,SB,BP,JB,AE,SH","TB,SB,BP,JB,MJ,BS","TB,SB,BP,JB,AE,SB,AE","TB,SB,BP,JB,PS,AE","TB,SB,BP,JB,BS,MJ","TB,SB,BP,JB,AE,TT"],"items":["Tension Bow","Sorrowblade","Breaking Point","Situational Boots"]},{"key":"TB,BP,SB,AE","winRate":60.98,"pickRate":1.33,"variants":["TB,BP,SB,AE","TB,BP,SB,AE,JB","TB,BP,SB,AE,HC","TB,BP,SB,AE,TT","TB,BP,SB,AE,MJ","TB,BP,SB,AE,JB,MJ","TB,BP,SB,AE,MJ,JB","TB,BP,SB,AE,JB,TT,JB","TB,BP,SB,AE,SS","TB,BP,SB,AE,BS,SB,JB","TB,BP,SB,AE,HC,MJ","TB,BP,SB,AE,JB,BS","TB,BP,SB,AE,JB,SS,BS","TB,BP,SB,AE,PS,JB","TB,BP,SB,AE,JB,AE,SB","TB,BP,SB,AE,TT,WT","TB,BP,SB,AE,JB,PS","TB,BP,SB,AE,WT","TB,BP,SB,AE,SB","TB,BP,SB,AE,JB,TT","TB,BP,SB,AE,SB,WT","TB,BP,SB,AE,PS,JB,TT","TB,BP,SB,AE,JB,JB","TB,BP,SB,AE,MJ,JB,TT","TB,BP,SB,AE,BS","TB,BP,SB,AE,JB,TT,TB,BS","TB,BP,SB,AE,TT,HC","TB,BP,SB,AE,JB,MJ,TT","TB,BP,SB,AE,MJ,HC","TB,BP,SB,AE,AP,HC","TB,BP,SB,AE,PS,HC","TB,BP,SB,AE,JB,SC","TB,BP,SB,AE,SB,JB","TB,BP,SB,AE,BS,JB","TB,BP,SB,AE,JB,SS","TB,BP,SB,AE,HC,TT"],"items":["Tension Bow","Breaking Point","Sorrowblade","Aegis"]},{"key":"TB,SB,TT,*","winRate":59.57,"pickRate":0.91,"variants":["TB,SB,TT,AE,BP,JB","TB,SB,TT,AE,MJ,JB","TB,SB,TT,AE,PS","TB,SB,TT,AE","TB,SB,TT,AE,AP","TB,SB,TT,AE,MJ","TB,SB,TT,AE,JB","TB,SB,TT,AE,JB,BP","TB,SB,TT,AE,WT,MJ,BS","TB,SB,TT,AE,MJ,SB,JB,BS","TB,SB,TT,AE,MJ,BP","TB,SB,TT,AE,SM,JB","TB,SB,TT,AE,BP,HC","TB,SB,TT,AE,BP","TB,SB,TT,AE,HC,BP","TB,SB,TT,AE,HC","TB,SB,TT,AE,JB,SS","TB,SB,TT,AE,PS,HC","TB,SB,TT,AE,HC,TT,BP","TB,SB,TT,AE,JB,AP,MJ","TB,SB,TT,AE,HC,PS,TT","TB,SB,TT,AE,MJ,HC","TB,SB,TT,AE,HC,HC,HC,HC","TB,SB,TT,AE,BS","TB,SB,TT,AE,HC,TT","TB,SB,TT,AE,JB,AP","TB,SB,TT,AE,JB,BS","TB,SB,TT,AE,MJ,WT,BP,TT","TB,SB,TT,AE,WT","TB,SB,TT,AE,JB,MJ","TB,SB,TT,SH","TB,SB,TT,SH,JB","TB,SB,TT,SH,WT","TB,SB,TT,SH,HC","TB,SB,TT,SH,AE,HC","TB,SB,TT,MJ","TB,SB,TT,MJ,JB","TB,SB,TT,MJ,AE","TB,SB,TT,MJ,AE,WT","TB,SB,TT,MJ,HC","TB,SB,TT,MJ,WT,AE,SB","TB,SB,TT,MJ,JB,BP,AE","TB,SB,TT,MJ,JB,AE","TB,SB,TT,MJ,JB,BP","TB,SB,TT,MJ,AE,HC","TB,SB,TT,MJ,CB,WT","TB,SB,TT,MJ,PS,JB","TB,SB,TT,MJ,BS,JB","TB,SB,TT,MJ,AE,JB","TB,SB,TT,AP,JB"],"items":["Tension Bow","Sorrowblade","Tornado Trigger","Situational Defense"]},{"key":"TB,SB,*,**","winRate":58.57,"pickRate":0.91,"variants":["TB,SB,AE,HC","TB,SB,AE,HC,BS,SB","TB,SB,AE,HC,TT,BS","TB,SB,AE,HC,BP,BS","TB,SB,AE,HC,TT","TB,SB,AE,HC,BP","TB,SB,AE,HC,TT,PS,BP","TB,SB,AE,HC,BS,MJ","TB,SB,AE,HC,BP,PS","TB,SB,AE,HC,PS","TB,SB,AE,HC,BP,SH,FR","TB,SB,AE,HC,BP,TT","TB,SB,AE,HC,MJ","TB,SB,MJ,JB,BS,AE","TB,SB,MJ,JB,BP,PS","TB,SB,MJ,JB,AE","TB,SB,MJ,JB","TB,SB,MJ,JB,TT","TB,SB,MJ,JB,BS","TB,SB,AE,JB","TB,SB,AE,JB,MJ","TB,SB,AE,JB,TT,MJ","TB,SB,AE,JB,BS","TB,SB,AE,JB,BP","TB,SB,AE,JB,TT","TB,SB,AE,JB,SC","TB,SB,AE,JB,PS","TB,SB,AE,JB,SB","TB,SB,AE,JB,SM","TB,SB,AE,JB,BP,MJ","TB,SB,AE,JB,CB","TB,SB,MJ,HC","TB,SB,MJ,HC,AE,BP","TB,SB,MJ,HC,BP,AE","TB,SB,SH,JB","TB,SB,SH,JB,PS,BP","TB,SB,SH,JB,TT","TB,SB,SH,HC,BP","TB,SB,SH,HC","TB,SB,AP,JB"],"items":["Tension Bow","Sorrowblade","Situational Defense","Situational Boots"]},{"key":"TB,SB,**,BP","winRate":65.89,"pickRate":0.84,"variants":["TB,SB,JB,BP","TB,SB,JB,BP,AE","TB,SB,JB,BP,SH,SS","TB,SB,JB,BP,AE,PS,SM,PS","TB,SB,JB,BP,SS","TB,SB,JB,BP,AE,MJ","TB,SB,JB,BP,AE,TT","TB,SB,JB,BP,AE,MJ,SB","TB,SB,JB,BP,PS,AE","TB,SB,JB,BP,CB","TB,SB,JB,BP,AP","TB,SB,JB,BP,MJ,AE","TB,SB,JB,BP,AE,JB","TB,SB,JB,BP,SH","TB,SB,HC,BP","TB,SB,HC,BP,AE,MJ","TB,SB,HC,BP,BS","TB,SB,HC,BP,AE","TB,SB,HC,BP,AE,MJ,PS","TB,SB,HC,BP,TT,AE","TB,SB,HC,BP,AP","TB,SB,HC,BP,MJ","TB,SB,HC,BP,AE,TT","TB,SB,HC,BP,AE,TT,HC,HC","TB,SB,HC,BP,MJ,AE","TB,SB,HC,BP,AE,BS"],"items":["Tension Bow","Sorrowblade","Situational Boots","Breaking Point"]},{"key":"TB,SB,**,*","winRate":60.66,"pickRate":0.79,"variants":["TB,SB,HC,SH","TB,SB,JB,AE","TB,SB,JB,AE,SB","TB,SB,JB,AE,TT,TT","TB,SB,JB,AE,TT,BP","TB,SB,JB,AE,BP,MJ","TB,SB,JB,AE,PS","TB,SB,JB,AE,TT","TB,SB,JB,AE,MJ","TB,SB,JB,AE,BP","TB,SB,JB,AE,BS","TB,SB,JB,AE,MJ,BP","TB,SB,JB,AE,FR","TB,SB,HC,MJ,PS","TB,SB,HC,MJ","TB,SB,HC,MJ,AE","TB,SB,HC,MJ,BS","TB,SB,HC,MJ,BM,DE","TB,SB,JB,MJ,BS","TB,SB,JB,MJ","TB,SB,JB,MJ,AE","TB,SB,JB,MJ,BP,BS","TB,SB,JB,MJ,SB,AE","TB,SB,JB,MJ,SS,PS","TB,SB,JB,MJ,TT","TB,SB,JB,MJ,AE,TT","TB,SB,JB,MJ,AE,PS","TB,SB,JB,SH,BP,AE","TB,SB,JB,SH,BP,BS","TB,SB,JB,SH","TB,SB,HC,AP","TB,SB,HC,AP,SB","TB,SB,HC,AE,BS,MJ","TB,SB,HC,AE","TB,SB,HC,AE,MJ","TB,SB,HC,AE,BP,MJ","TB,SB,HC,AE,PS","TB,SB,HC,AE,BP","TB,SB,HC,AE,BP,PS","TB,SB,HC,AE,AP","TB,SB,HC,AE,BP,BS","TB,SB,HC,AE,PS,BS","TB,SB,HC,AE,BS","TB,SB,HC,AE,TT"],"items":["Tension Bow","Sorrowblade","Situational Boots","Situational Defense"]},{"key":"TB,BP,*,**","winRate":56.9,"pickRate":0.75,"variants":["TB,BP,AE,HC","TB,BP,AE,HC,TT","TB,BP,AE,HC,SB,MJ","TB,BP,AE,HC,SB","TB,BP,AE,HC,AP","TB,BP,AE,HC,FR","TB,BP,AE,HC,SB,BS","TB,BP,AE,HC,SB,TT","TB,BP,AE,HC,MJ","TB,BP,AE,HC,MJ,SM,BS","TB,BP,AE,HC,SB,SS,TT","TB,BP,AE,HC,SB,BS,TT","TB,BP,AE,JB","TB,BP,AE,JB,MJ","TB,BP,AE,JB,SB","TB,BP,AE,JB,PS","TB,BP,AE,JB,SB,TT","TB,BP,AE,JB,SB,SS","TB,BP,AE,JB,WT","TB,BP,AE,JB,SB,MJ","TB,BP,AE,JB,PS,MJ","TB,BP,AE,JB,BS,SB","TB,BP,AE,JB,TT,WT","TB,BP,AE,JB,SC,SC,SC,SC,SC","TB,BP,AE,JB,SM,FR","TB,BP,AE,JB,TT","TB,BP,SH,JB","TB,BP,SH,JB,SS","TB,BP,SH,JB,SB","TB,BP,MJ,HC,AE,SB","TB,BP,MJ,HC,AE","TB,BP,MJ,HC,HC","TB,BP,MJ,HC,TT","TB,BP,MJ,HC,SB","TB,BP,MJ,HC","TB,BP,MJ,JB,SB,AE","TB,BP,MJ,JB","TB,BP,MJ,JB,FR","TB,BP,MJ,JB,SB","TB,BP,MJ,JB,AE,BS","TB,BP,SH,HC"],"items":["Tension Bow","Breaking Point","Situational Defense","Situational Boots"]},{"key":"TB,BP,AE,SB","winRate":58.95,"pickRate":0.62,"variants":["TB,BP,AE,SB,MJ,JB","TB,BP,AE,SB,BS","TB,BP,AE,SB,HC,SB","TB,BP,AE,SB","TB,BP,AE,SB,HC,MJ","TB,BP,AE,SB,SC","TB,BP,AE,SB,JB","TB,BP,AE,SB,JB,BS","TB,BP,AE,SB,BS,WT,SM","TB,BP,AE,SB,JB,MJ","TB,BP,AE,SB,PS,HC","TB,BP,AE,SB,TT","TB,BP,AE,SB,HC","TB,BP,AE,SB,TT,JB,TB,BP","TB,BP,AE,SB,JB,SS","TB,BP,AE,SB,WT","TB,BP,AE,SB,HC,MJ,JB","TB,BP,AE,SB,MJ","TB,BP,AE,SB,HC,TT","TB,BP,AE,SB,JB,JB","TB,BP,AE,SB,JB,SH","TB,BP,AE,SB,MJ,HC","TB,BP,AE,SB,JB,NG,NG,SC,SL"],"items":["Tension Bow","Breaking Point","Aegis","Sorrowblade"]},{"key":"TB,BP,SB,**","winRate":60,"pickRate":0.58,"variants":["TB,BP,SB,HC,AE,BS","TB,BP,SB,HC,SB,MJ","TB,BP,SB,HC","TB,BP,SB,HC,FR,SS,BS","TB,BP,SB,HC,SS","TB,BP,SB,HC,MJ","TB,BP,SB,HC,PS","TB,BP,SB,HC,AE","TB,BP,SB,HC,SH","TB,BP,SB,HC,MJ,BS,AE","TB,BP,SB,HC,TT,AE","TB,BP,SB,JB","TB,BP,SB,JB,AE","TB,BP,SB,JB,AE,BS","TB,BP,SB,JB,AE,TT","TB,BP,SB,JB,TT","TB,BP,SB,JB,AE,PS","TB,BP,SB,JB,SH","TB,BP,SB,JB,PS,AE,TT","TB,BP,SB,JB,SH,SM","TB,BP,SB,JB,AE,MJ,TT","TB,BP,SB,JB,AE,SM,SB","TB,BP,SB,JB,MJ","TB,BP,SB,JB,MJ,AE","TB,BP,SB,JB,SL","TB,BP,SB,JB,TT,AE","TB,BP,SB,JB,AE,MJ","TB,BP,SB,JB,BS,MJ"],"items":["Tension Bow","Breaking Point","Sorrowblade","Situational Boots"]},{"key":"TB,SB,TT,**","winRate":63.41,"pickRate":0.53,"variants":["TB,SB,TT,JB","TB,SB,TT,JB,AE","TB,SB,TT,JB,SH","TB,SB,TT,JB,BP,SS","TB,SB,TT,JB,SM,AE","TB,SB,TT,JB,SB","TB,SB,TT,JB,BS","TB,SB,TT,JB,BP","TB,SB,TT,JB,MJ","TB,SB,TT,JB,AE,CB","TB,SB,TT,JB,WT","TB,SB,TT,JB,TT,AE","TB,SB,TT,HC,MJ","TB,SB,TT,HC,SB","TB,SB,TT,HC","TB,SB,TT,HC,AE","TB,SB,TT,HC,SH","TB,SB,TT,HC,MJ,AE","TB,SB,TT,HC,SF"],"items":["Tension Bow","Sorrowblade","Tornado Trigger","Situational Boots"]},{"key":"SB,BP,*,**","winRate":54.67,"pickRate":0.49,"variants":["SB,BP,AE,JB,BS","SB,BP,AE,JB","SB,BP,AE,JB,TT","SB,BP,AE,JB,TB,TB","SB,BP,AE,JB,MJ","SB,BP,AE,JB,BS,MJ","SB,BP,AE,JB,JB,AE","SB,BP,AE,JB,SB","SB,BP,AE,JB,PS,MJ","SB,BP,AE,JB,TB","SB,BP,AE,JB,PS,TB","SB,BP,AE,JB,PS","SB,BP,AE,HC,BS","SB,BP,AE,HC","SB,BP,AE,HC,TB","SB,BP,AE,HC,PS","SB,BP,AE,HC,MJ","SB,BP,MJ,JB,BS,AE","SB,BP,MJ,JB","SB,BP,MJ,JB,AE","SB,BP,MJ,HC"],"items":["Sorrowblade","Breaking Point","Situational Defense","Situational Boots"]},{"key":"TB,BP,**,SB","winRate":53.62,"pickRate":0.45,"variants":["TB,BP,HC,SB","TB,BP,HC,SB,AE","TB,BP,HC,SB,PS,SH","TB,BP,HC,SB,PS","TB,BP,HC,SB,MJ,AE,TT","TB,BP,HC,SB,TT","TB,BP,HC,SB,MJ","TB,BP,HC,SB,SS","TB,BP,HC,SB,AE,MJ","TB,BP,HC,SB,AP","TB,BP,HC,SB,MJ,AE","TB,BP,JB,SB","TB,BP,JB,SB,BS,AE","TB,BP,JB,SB,AE,TT","TB,BP,JB,SB,MJ","TB,BP,JB,SB,AE","TB,BP,JB,SB,AE,SH","TB,BP,JB,SB,AE,PS","TB,BP,JB,SB,TT,AE","TB,BP,JB,SB,PS","TB,BP,JB,SB,BS","TB,BP,JB,SB,MJ,AE","TB,BP,JB,SB,MJ,AE,HC","TB,BP,JB,SB,PS,TT","TB,BP,JB,SB,AE,MJ,PS","TB,BP,JB,SB,AE,MJ"],"items":["Tension Bow","Breaking Point","Situational Boots","Sorrowblade"]},{"key":"TB,BP,**,*","winRate":57.58,"pickRate":0.43,"variants":["TB,BP,HC,AE","TB,BP,HC,AE,MJ","TB,BP,HC,AE,SB","TB,BP,HC,AE,PS,SB","TB,BP,HC,AE,SB,MJ","TB,BP,HC,AE,BS","TB,BP,HC,AE,TT,SB","TB,BP,HC,AE,TT","TB,BP,JB,AE,SB,TT","TB,BP,JB,AE","TB,BP,JB,AE,JB,SM","TB,BP,JB,AE,SB","TB,BP,JB,AE,BS","TB,BP,JB,MJ","TB,BP,JB,MJ,AE,TT","TB,BP,JB,MJ,JB","TB,BP,JB,MJ,AE","TB,BP,JB,MJ,SB","TB,BP,JB,MJ,SB,AE","TB,BP,HC,MJ,AE","TB,BP,HC,MJ","TB,BP,HC,MJ,BS","TB,BP,HC,SH","TB,BP,HC,SH,SB","TB,BP,JB,SH"],"items":["Tension Bow","Breaking Point","Situational Boots","Situational Defense"]},{"key":"TB,**,SB,BP","winRate":65.57,"pickRate":0.4,"variants":["TB,JB,SB,BP,AE","TB,JB,SB,BP,AE,MJ","TB,JB,SB,BP","TB,JB,SB,BP,MJ","TB,JB,SB,BP,FR","TB,JB,SB,BP,MJ,AE,SB","TB,JB,SB,BP,AE,PS","TB,JB,SB,BP,AE,TT","TB,HC,SB,BP,AE","TB,HC,SB,BP,AE,SM","TB,HC,SB,BP,AE,MJ","TB,HC,SB,BP,SM","TB,HC,SB,BP,AE,JB,TT","TB,HC,SB,BP,SH","TB,HC,SB,BP","TB,HC,SB,BP,PS","TB,HC,SB,BP,AE,TT","TB,HC,SB,BP,AE,AP","TB,HC,SB,BP,SH,TT"],"items":["Tension Bow","Situational Boots","Sorrowblade","Breaking Point"]},{"key":"TB,PS,BP,AE","winRate":49.15,"pickRate":0.38,"variants":["TB,PS,BP,AE","TB,PS,BP,AE,SB,TT,JB","TB,PS,BP,AE,JB,SS","TB,PS,BP,AE,JB","TB,PS,BP,AE,MJ,JB","TB,PS,BP,AE,SB,JB","TB,PS,BP,AE,MJ","TB,PS,BP,AE,MJ,HC","TB,PS,BP,AE,HC","TB,PS,BP,AE,BS,JB","TB,PS,BP,AE,MJ,JB,SB,BS","TB,PS,BP,AE,HC,SM","TB,PS,BP,AE,WT","TB,PS,BP,AE,BS,HC","TB,PS,BP,AE,HC,MJ","TB,PS,BP,AE,TT,JB,BS","TB,PS,BP,AE,JB,SB","TB,PS,BP,AE,BS","TB,PS,BP,AE,JB,SH","TB,PS,BP,AE,SB,JB,BS"],"items":["Tension Bow","Poisoned Shiv","Breaking Point","Aegis"]},{"key":"SB,BP,PS,AE","winRate":66.67,"pickRate":0.35,"variants":["SB,BP,PS,AE","SB,BP,PS,AE,TT","SB,BP,PS,AE,BS,JB","SB,BP,PS,AE,BS,JB,TT","SB,BP,PS,AE,MJ,JB","SB,BP,PS,AE,MJ,WT","SB,BP,PS,AE,BS","SB,BP,PS,AE,WT,SS,TB,BS","SB,BP,PS,AE,HC,MJ","SB,BP,PS,AE,JB,MJ","SB,BP,PS,AE,JB","SB,BP,PS,AE,JB,BS","SB,BP,PS,AE,BS,JB,MJ"],"items":["Sorrowblade","Breaking Point","Poisoned Shiv","Aegis"]},{"key":"SB,TB,BP,AE","winRate":61.11,"pickRate":0.35,"variants":["SB,TB,BP,AE,JB,MJ","SB,TB,BP,AE,WT","SB,TB,BP,AE,MJ,WT","SB,TB,BP,AE,JB","SB,TB,BP,AE,PS","SB,TB,BP,AE,PS,JB","SB,TB,BP,AE,BS,HC","SB,TB,BP,AE,JB,MJ,BS","SB,TB,BP,AE","SB,TB,BP,AE,MJ","SB,TB,BP,AE,JB,BS","SB,TB,BP,AE,JB,TT,FR","SB,TB,BP,AE,TT,JB","SB,TB,BP,AE,JB,PS","SB,TB,BP,AE,HC,TT,SH,BS","SB,TB,BP,AE,JB,SM","SB,TB,BP,AE,HC","SB,TB,BP,AE,HC,SM"],"items":["Sorrowblade","Tension Bow","Breaking Point","Aegis"]},{"key":"SG,CW,BM,SH","winRate":40.74,"pickRate":0.35,"variants":["SG,CW,BM,SH,JB","SG,CW,BM,SH","SG,CW,BM,SH,DE,JB","SG,CW,BM,SH,HC","SG,CW,BM,SH,DE","SG,CW,BM,SH,SG","SG,CW,BM,SH,JB,DE","SG,CW,BM,SH,DE,JB,SG"],"items":["Shatterglass","Clockwork","Broken Myth","Slumbering Husk"]},{"key":"TB,SB,BP,PS","winRate":52.94,"pickRate":0.33,"variants":["TB,SB,BP,PS,JB","TB,SB,BP,PS","TB,SB,BP,PS,HC,AE","TB,SB,BP,PS,AE","TB,SB,BP,PS,AE,HC","TB,SB,BP,PS,JB,AE","TB,SB,BP,PS,AE,JB,BS,SM","TB,SB,BP,PS,WT","TB,SB,BP,PS,AE,BS,WT","TB,SB,BP,PS,JB,MJ","TB,SB,BP,PS,BS,AE","TB,SB,BP,PS,AE,WT","TB,SB,BP,PS,MJ","TB,SB,BP,PS,HC","TB,SB,BP,PS,AE,JB"],"items":["Tension Bow","Sorrowblade","Breaking Point","Poisoned Shiv"]},{"key":"TB,SB,AE,TT","winRate":41.18,"pickRate":0.33,"variants":["TB,SB,AE,TT","TB,SB,AE,TT,WT","TB,SB,AE,TT,JB","TB,SB,AE,TT,TT,HC","TB,SB,AE,TT,MJ","TB,SB,AE,TT,HC","TB,SB,AE,TT,HC,TT","TB,SB,AE,TT,FR","TB,SB,AE,TT,JB,MJ","TB,SB,AE,TT,HC,PS","TB,SB,AE,TT,BP","TB,SB,AE,TT,JB,BP","TB,SB,AE,TT,BS","TB,SB,AE,TT,AP"],"items":["Tension Bow","Sorrowblade","Aegis","Tornado Trigger"]},{"key":"TB,BP,PS,*","winRate":54,"pickRate":0.32,"variants":["TB,BP,PS,AE","TB,BP,PS,AE,SB","TB,BP,PS,AE,JB","TB,BP,PS,AE,HC","TB,BP,PS,AE,MJ,WT","TB,BP,PS,AE,HC,SB","TB,BP,PS,AE,AE","TB,BP,PS,AE,WT","TB,BP,PS,AE,MJ,JB","TB,BP,PS,AE,WT,SB","TB,BP,PS,AE,BS,MJ","TB,BP,PS,AE,MJ","TB,BP,PS,AE,JB,SB","TB,BP,PS,AE,JB,SS,TT","TB,BP,PS,MJ","TB,BP,PS,MJ,JB","TB,BP,PS,MJ,JB,AE,JB","TB,BP,PS,SH","TB,BP,PS,AP,WT"],"items":["Tension Bow","Breaking Point","Poisoned Shiv","Situational Defense"]},{"key":"TB,SB,*,*","winRate":40.82,"pickRate":0.32,"variants":["TB,SB,AE,MJ","TB,SB,AE,MJ,JB","TB,SB,AE,MJ,WT","TB,SB,AE,MJ,BP,JB","TB,SB,AE,MJ,BP,WT","TB,SB,AE,MJ,BP","TB,SB,AE,MJ,HC,BP","TB,SB,AE,MJ,JB,SB","TB,SB,AE,MJ,JB,BP","TB,SB,AE,MJ,HC","TB,SB,AE,MJ,JB,BS,PS","TB,SB,AE,MJ,AE,FR","TB,SB,AE,MJ,HC,BS","TB,SB,AE,MJ,BP,BS,HC","TB,SB,AE,SH","TB,SB,MJ,AE,BP","TB,SB,MJ,AE","TB,SB,MJ,AE,JB","TB,SB,MJ,AE,BP,JB","TB,SB,MJ,SH,BS","TB,SB,SH,AP,BP,JB"],"items":["Tension Bow","Sorrowblade","Situational Defense","Situational Defense"]},{"key":"TB,PS,SB,*","winRate":60.42,"pickRate":0.31,"variants":["TB,PS,SB,MJ,AE,JB","TB,PS,SB,MJ,TT,WT","TB,PS,SB,MJ","TB,PS,SB,MJ,JB,BP","TB,PS,SB,MJ,HC","TB,PS,SB,MJ,JB","TB,PS,SB,MJ,AE","TB,PS,SB,AE","TB,PS,SB,AE,TT,WT","TB,PS,SB,AE,BP,JB","TB,PS,SB,AE,MJ,BP,JB,BS","TB,PS,SB,AE,HC","TB,PS,SB,AE,WT,BS","TB,PS,SB,AE,WT,BP","TB,PS,SB,AE,MJ,BS","TB,PS,SB,AE,MJ,JB,BS","TB,PS,SB,AE,WT","TB,PS,SB,AE,BP","TB,PS,SB,AE,BP,AP","TB,PS,SB,AE,HC,MJ","TB,PS,SB,AE,JB","TB,PS,SB,AE,MJ,HC","TB,PS,SB,AE,BP,JB,FR","TB,PS,SB,AE,MJ","TB,PS,SB,AE,HC,BP","TB,PS,SB,AE,AE,HC"],"items":["Tension Bow","Poisoned Shiv","Sorrowblade","Situational Defense"]},{"key":"TB,SB,PS,AE","winRate":50,"pickRate":0.31,"variants":["TB,SB,PS,AE","TB,SB,PS,AE,WT","TB,SB,PS,AE,JB","TB,SB,PS,AE,BS,JB","TB,SB,PS,AE,BP,HC","TB,SB,PS,AE,JB,BP","TB,SB,PS,AE,MJ,JB","TB,SB,PS,AE,BP,JB,SB","TB,SB,PS,AE,HC","TB,SB,PS,AE,BP,JB","TB,SB,PS,AE,TT","TB,SB,PS,AE,JB,BP,BS,SM","TB,SB,PS,AE,JB,WT","TB,SB,PS,AE,MJ,BP","TB,SB,PS,AE,HC,MJ","TB,SB,PS,AE,AP,HC"],"items":["Tension Bow","Sorrowblade","Poisoned Shiv","Aegis"]},{"key":"SB,BP,**,*","winRate":67.39,"pickRate":0.3,"variants":["SB,BP,HC,MJ","SB,BP,HC,MJ,AE,BS","SB,BP,JB,AE,MJ,JB","SB,BP,JB,AE,AP","SB,BP,JB,AE","SB,BP,JB,AE,BS","SB,BP,JB,AE,MJ","SB,BP,JB,AE,TT","SB,BP,HC,AE","SB,BP,HC,AE,MJ","SB,BP,HC,AE,TB","SB,BP,HC,AE,BS,MJ","SB,BP,JB,MJ,PS","SB,BP,JB,MJ,AE","SB,BP,JB,MJ","SB,BP,JB,MJ,AE,PS","SB,BP,JB,SH"],"items":["Sorrowblade","Breaking Point","Situational Boots","Situational Defense"]},{"key":"TB,SB,BP,TT","winRate":68.18,"pickRate":0.29,"variants":["TB,SB,BP,TT","TB,SB,BP,TT,JB,AE","TB,SB,BP,TT,AE,JB","TB,SB,BP,TT,AE,WT","TB,SB,BP,TT,JB","TB,SB,BP,TT,AE","TB,SB,BP,TT,MJ","TB,SB,BP,TT,WT","TB,SB,BP,TT,HC,AE","TB,SB,BP,TT,JB,MJ","TB,SB,BP,TT,AE,HC"],"items":["Tension Bow","Sorrowblade","Breaking Point","Tornado Trigger"]},{"key":"TB,SB,PS,BP","winRate":59.52,"pickRate":0.27,"variants":["TB,SB,PS,BP,BS","TB,SB,PS,BP,HC,AE","TB,SB,PS,BP,AE,HC","TB,SB,PS,BP","TB,SB,PS,BP,AE","TB,SB,PS,BP,SH","TB,SB,PS,BP,JB,AE","TB,SB,PS,BP,AE,JB","TB,SB,PS,BP,AE,JB,TT","TB,SB,PS,BP,JB,TT","TB,SB,PS,BP,WT","TB,SB,PS,BP,HC","TB,SB,PS,BP,MJ,JB,NG,NG,NG,NG","TB,SB,PS,BP,AE,JB,MJ"],"items":["Tension Bow","Sorrowblade","Poisoned Shiv","Breaking Point"]},{"key":"TB,**,SB,*","winRate":26.83,"pickRate":0.27,"variants":["TB,HC,SB,AE","TB,HC,SB,AE,BP","TB,HC,SB,AE,PS","TB,HC,SB,AE,SM","TB,HC,SB,AE,PS,TT","TB,HC,SB,AE,SB","TB,HC,SB,AE,BP,AP","TB,HC,SB,AE,BS","TB,HC,SB,AE,SS","TB,HC,SB,AE,BP,JB,AP","TB,HC,SB,AE,MJ,BP","TB,HC,SB,AE,PS,SF,BP,SH","TB,HC,SB,AP","TB,JB,SB,AE,BP","TB,JB,SB,AE","TB,JB,SB,AE,BP,MJ","TB,JB,SB,AE,TT","TB,JB,SB,AE,PS","TB,JB,SB,AE,TT,SS","TB,JB,SB,SH,TT","TB,HC,SB,MJ","TB,HC,SB,MJ,TT,BP","TB,HC,SB,SH,BP,SM,TT"],"items":["Tension Bow","Situational Boots","Sorrowblade","Situational Defense"]},{"key":"SB,PS,BP,AE","winRate":75,"pickRate":0.26,"variants":["SB,PS,BP,AE","SB,PS,BP,AE,HC","SB,PS,BP,AE,MJ,HC","SB,PS,BP,AE,TT,JB","SB,PS,BP,AE,TT","SB,PS,BP,AE,JB,BS","SB,PS,BP,AE,JB,MJ","SB,PS,BP,AE,JB,MJ,BS","SB,PS,BP,AE,WT","SB,PS,BP,AE,WT,MJ","SB,PS,BP,AE,JB","SB,PS,BP,AE,TB,JB","SB,PS,BP,AE,TT,HC","SB,PS,BP,AE,BS","SB,PS,BP,AE,MJ,JB","SB,PS,BP,AE,MJ","SB,PS,BP,AE,HC,SB"],"items":["Sorrowblade","Poisoned Shiv","Breaking Point","Aegis"]},{"key":"TB,SB,PS,**","winRate":57.5,"pickRate":0.26,"variants":["TB,SB,PS,HC","TB,SB,PS,HC,BP,AE,BS","TB,SB,PS,HC,BP,SH","TB,SB,PS,HC,MJ","TB,SB,PS,HC,AE","TB,SB,PS,JB,BP,SH","TB,SB,PS,JB,BP,AE","TB,SB,PS,JB","TB,SB,PS,JB,MJ,AE","TB,SB,PS,JB,AE,BP","TB,SB,PS,JB,TT","TB,SB,PS,JB,AE,SS","TB,SB,PS,JB,BP,MJ","TB,SB,PS,JB,MJ,BP,TB,HC","TB,SB,PS,JB,BP","TB,SB,PS,JB,TT,MJ","TB,SB,PS,JB,AE","TB,SB,PS,JB,AE,MJ","TB,SB,PS,JB,BS,FR"],"items":["Tension Bow","Sorrowblade","Poisoned Shiv","Situational Boots"]},{"key":"TB,BP,*,*","winRate":36.84,"pickRate":0.25,"variants":["TB,BP,AE,AP","TB,BP,AE,AP,SB","TB,BP,AE,AP,JB","TB,BP,AE,MJ","TB,BP,AE,MJ,JB,BS","TB,BP,AE,MJ,JB","TB,BP,AE,MJ,SB,JB","TB,BP,AE,MJ,HC,SS,JB","TB,BP,AE,MJ,SB","TB,BP,AE,MJ,HC","TB,BP,MJ,AE","TB,BP,MJ,AE,WT","TB,BP,MJ,AE,JB","TB,BP,MJ,AE,SB","TB,BP,MJ,AE,JB,BS","TB,BP,AE,SH,JB,SB","TB,BP,AE,SH","TB,BP,AE,SH,JB"],"items":["Tension Bow","Breaking Point","Situational Defense","Situational Defense"]},{"key":"TB,PS,BP,**","winRate":66.67,"pickRate":0.21,"variants":["TB,PS,BP,JB","TB,PS,BP,JB,AE","TB,PS,BP,JB,AE,WT","TB,PS,BP,JB,AE,MJ","TB,PS,BP,JB,SH","TB,PS,BP,JB,AE,SB","TB,PS,BP,JB,MJ,AE","TB,PS,BP,HC,AE,MJ","TB,PS,BP,HC","TB,PS,BP,HC,AE","TB,PS,BP,HC,AE,SB","TB,PS,BP,HC,AE,JB","TB,PS,BP,HC,SS,AE","TB,PS,BP,HC,SB,AE","TB,PS,BP,HC,AP","TB,PS,BP,HC,MJ,SB,BS"],"items":["Tension Bow","Poisoned Shiv","Breaking Point","Situational Boots"]},{"key":"TB,SB,*,PS","winRate":53.13,"pickRate":0.21,"variants":["TB,SB,AE,PS,JB,BP","TB,SB,AE,PS,JB","TB,SB,AE,PS,MJ,JB","TB,SB,AE,PS","TB,SB,AE,PS,JB,MJ","TB,SB,AE,PS,HC,MJ","TB,SB,AE,PS,AP,JB","TB,SB,AE,PS,BP,JB","TB,SB,AE,PS,BP","TB,SB,AE,PS,JB,BS,TT","TB,SB,AE,PS,SC,JB,SB,TB","TB,SB,AE,PS,HC","TB,SB,SH,PS,HC,SB","TB,SB,SH,PS,MJ,JB","TB,SB,SH,PS,TT","TB,SB,SH,PS","TB,SB,MJ,PS,AE","TB,SB,MJ,PS,BS","TB,SB,MJ,PS"],"items":["Tension Bow","Sorrowblade","Situational Defense","Poisoned Shiv"]},{"key":"SB,PS,BP,**","winRate":70,"pickRate":0.19,"variants":["SB,PS,BP,JB","SB,PS,BP,JB,AE,TB","SB,PS,BP,JB,MJ","SB,PS,BP,JB,AE","SB,PS,BP,JB,MJ,AE","SB,PS,BP,HC,AE,BS,MJ","SB,PS,BP,HC,SH,BS","SB,PS,BP,HC","SB,PS,BP,HC,AE","SB,PS,BP,HC,BS,AE","SB,PS,BP,HC,TT,AE"],"items":["Sorrowblade","Poisoned Shiv","Breaking Point","Situational Boots"]},{"key":"TB,BP,AE,TT","winRate":65.52,"pickRate":0.19,"variants":["TB,BP,AE,TT,JB,SB","TB,BP,AE,TT","TB,BP,AE,TT,JB","TB,BP,AE,TT,SB","TB,BP,AE,TT,SM","TB,BP,AE,TT,HC","TB,BP,AE,TT,JB,PS,SB","TB,BP,AE,TT,HC,BS","TB,BP,AE,TT,JB,SM","TB,BP,AE,TT,SB,JB"],"items":["Tension Bow","Breaking Point","Aegis","Tornado Trigger"]},{"key":"TB,SB,**,TT","winRate":62.07,"pickRate":0.19,"variants":["TB,SB,HC,TT","TB,SB,HC,TT,AE,MJ","TB,SB,HC,TT,MJ,CB","TB,SB,HC,TT,SH","TB,SB,JB,TT","TB,SB,JB,TT,AE","TB,SB,JB,TT,SB","TB,SB,JB,TT,PS","TB,SB,JB,TT,MJ","TB,SB,JB,TT,AE,SM","TB,SB,JB,TT,TT","TB,SB,JB,TT,CB,TT","TB,SB,JB,TT,SH","TB,SB,JB,TT,AE,SB"],"items":["Tension Bow","Sorrowblade","Situational Boots","Tornado Trigger"]},{"key":"TB,BP,TT,**","winRate":62.07,"pickRate":0.19,"variants":["TB,BP,TT,JB","TB,BP,TT,JB,AE","TB,BP,TT,JB,AE,PS","TB,BP,TT,JB,SB","TB,BP,TT,JB,SH","TB,BP,TT,JB,TT,AE","TB,BP,TT,HC,SH,PS,SB","TB,BP,TT,HC","TB,BP,TT,HC,PS","TB,BP,TT,HC,PS,AE","TB,BP,TT,HC,AE,SB","TB,BP,TT,HC,AE,MJ","TB,BP,TT,HC,AE"],"items":["Tension Bow","Breaking Point","Tornado Trigger","Situational Boots"]},{"key":"TB,PS,**,*","winRate":58.62,"pickRate":0.19,"variants":["TB,PS,HC,SH","TB,PS,JB,SH","TB,PS,JB,SH,MJ","TB,PS,HC,AE","TB,PS,HC,AE,BP","TB,PS,HC,AE,SB,MJ","TB,PS,HC,AE,SB","TB,PS,HC,AE,MJ,BP","TB,PS,JB,AE","TB,PS,JB,AE,SB,SH","TB,PS,JB,AE,BP,SB","TB,PS,JB,AE,SB","TB,PS,JB,MJ,AE","TB,PS,JB,MJ,BP,TT","TB,PS,JB,MJ,SB","TB,PS,HC,MJ,AE,BS","TB,PS,HC,MJ,TT"],"items":["Tension Bow","Poisoned Shiv","Situational Boots","Situational Defense"]},{"key":"TB,AE,SB,BP","winRate":48.28,"pickRate":0.19,"variants":["TB,AE,SB,BP,JB","TB,AE,SB,BP,TT,JB,BS","TB,AE,SB,BP","TB,AE,SB,BP,JB,BS","TB,AE,SB,BP,JB,TT","TB,AE,SB,BP,MJ","TB,AE,SB,BP,SH,JB","TB,AE,SB,BP,JB,MJ","TB,AE,SB,BP,JB,SH","TB,AE,SB,BP,HC"],"items":["Tension Bow","Aegis","Sorrowblade","Breaking Point"]},{"key":"TB,PS,**,SB","winRate":55.56,"pickRate":0.17,"variants":["TB,PS,HC,SB,BS,AE,SB","TB,PS,HC,SB,TT","TB,PS,HC,SB,BS","TB,PS,HC,SB,BP,MJ","TB,PS,HC,SB","TB,PS,HC,SB,AE","TB,PS,HC,SB,HC","TB,PS,HC,SB,AE,TT","TB,PS,HC,SB,TT,SH,TT","TB,PS,HC,SB,BP,CB","TB,PS,JB,SB","TB,PS,JB,SB,TT","TB,PS,JB,SB,SG,DE","TB,PS,JB,SB,AE","TB,PS,JB,SB,AE,BP","TB,PS,JB,SB,BP,AE","TB,PS,JB,SB,FR,CB"],"items":["Tension Bow","Poisoned Shiv","Situational Boots","Sorrowblade"]},{"key":"TB,SB,TT,BP","winRate":69.23,"pickRate":0.17,"variants":["TB,SB,TT,BP,MJ","TB,SB,TT,BP,AE,JB,MJ","TB,SB,TT,BP,MJ,AE,BS","TB,SB,TT,BP,HC","TB,SB,TT,BP","TB,SB,TT,BP,JB","TB,SB,TT,BP,WT","TB,SB,TT,BP,MJ,JB,BS","TB,SB,TT,BP,AE","TB,SB,TT,BP,AE,JB","TB,SB,TT,BP,JB,AE","TB,SB,TT,BP,JB,MJ","TB,SB,TT,BP,JB,BS"],"items":["Tension Bow","Sorrowblade","Tornado Trigger","Breaking Point"]},{"key":"TB,SB,BP,BS","winRate":57.69,"pickRate":0.17,"variants":["TB,SB,BP,BS","TB,SB,BP,BS,AE","TB,SB,BP,BS,AE,JB,PS","TB,SB,BP,BS,SM","TB,SB,BP,BS,JB,AE","TB,SB,BP,BS,AE,JB","TB,SB,BP,BS,JB","TB,SB,BP,BS,WT"],"items":["Tension Bow","Sorrowblade","Breaking Point","Bonesaw"]},{"key":"TB,PS,SB,**","winRate":53.85,"pickRate":0.17,"variants":["TB,PS,SB,HC,BS,SS","TB,PS,SB,HC,AE","TB,PS,SB,HC","TB,PS,SB,HC,SC,AE","TB,PS,SB,JB","TB,PS,SB,JB,MJ,CB","TB,PS,SB,JB,AE,TT","TB,PS,SB,JB,SH,AE","TB,PS,SB,JB,BP,MJ,SM","TB,PS,SB,JB,MJ,TT,BP","TB,PS,SB,JB,BP,BP","TB,PS,SB,JB,MJ,AE","TB,PS,SB,JB,BP,SH","TB,PS,SB,JB,AE","TB,PS,SB,JB,AE,BP"],"items":["Tension Bow","Poisoned Shiv","Sorrowblade","Situational Boots"]},{"key":"SB,TT,*,**","winRate":46.15,"pickRate":0.17,"variants":["SB,TT,AE,JB,TB,BP","SB,TT,AE,JB","SB,TT,AE,JB,MJ","SB,TT,AE,JB,TT","SB,TT,MJ,HC","SB,TT,SH,JB,BP","SB,TT,SH,JB","SB,TT,AE,HC","SB,TT,MJ,JB,BP","SB,TT,MJ,JB"],"items":["Sorrowblade","Tornado Trigger","Situational Defense","Situational Boots"]},{"key":"SB,TB,BP,**","winRate":87.5,"pickRate":0.16,"variants":["SB,TB,BP,JB,MJ","SB,TB,BP,JB,AE,MJ,BS","SB,TB,BP,JB","SB,TB,BP,JB,AE","SB,TB,BP,JB,PS,SH,SB","SB,TB,BP,JB,TT","SB,TB,BP,HC","SB,TB,BP,HC,PS","SB,TB,BP,HC,BS,AE","SB,TB,BP,HC,AE","SB,TB,BP,HC,TT","SB,TB,BP,HC,MJ","SB,TB,BP,HC,MJ,AE"],"items":["Sorrowblade","Tension Bow","Breaking Point","Situational Boots"]},{"key":"SB,BP,BS,AE","winRate":50,"pickRate":0.16,"variants":["SB,BP,BS,AE,HC","SB,BP,BS,AE","SB,BP,BS,AE,JB,PS","SB,BP,BS,AE,MJ,WT","SB,BP,BS,AE,JB","SB,BP,BS,AE,SM","SB,BP,BS,AE,MJ","SB,BP,BS,AE,TB,NG,NG,NG","SB,BP,BS,AE,JB,MJ"],"items":["Sorrowblade","Breaking Point","Bonesaw","Aegis"]},{"key":"SB,TT,**,*","winRate":41.67,"pickRate":0.16,"variants":["SB,TT,HC,SH,MJ","SB,TT,HC,AE","SB,TT,HC,AE,MJ","SB,TT,HC,AE,PS","SB,TT,HC,AE,MJ,BS","SB,TT,JB,AE","SB,TT,JB,AE,MJ","SB,TT,JB,AE,BP","SB,TT,JB,AE,BS","SB,TT,JB,SH","SB,TT,HC,MJ,AE","SB,TT,HC,MJ,SM"],"items":["Sorrowblade","Tornado Trigger","Situational Boots","Situational Defense"]},{"key":"SB,PS,AE,BP","winRate":56.52,"pickRate":0.15,"variants":["SB,PS,AE,BP,JB","SB,PS,AE,BP,TT,JB","SB,PS,AE,BP,MJ","SB,PS,AE,BP","SB,PS,AE,BP,HC","SB,PS,AE,BP,HC,MJ","SB,PS,AE,BP,MJ,HC","SB,PS,AE,BP,TT","SB,PS,AE,BP,HC,MJ,SH","SB,PS,AE,BP,HC,BS","SB,PS,AE,BP,TB,JB","SB,PS,AE,BP,HC,TB"],"items":["Sorrowblade","Poisoned Shiv","Aegis","Breaking Point"]},{"key":"SB,BP,PS,JB","winRate":68.18,"pickRate":0.14,"variants":["SB,BP,PS,JB,JB,JB","SB,BP,PS,JB","SB,BP,PS,JB,AE","SB,BP,PS,JB,BS,AE","SB,BP,PS,JB,MJ,AE","SB,BP,PS,JB,MJ","SB,BP,PS,JB,SG,SF","SB,BP,PS,JB,TB"],"items":["Sorrowblade","Breaking Point","Poisoned Shiv","Journey Boots"]},{"key":"TB,BP,PS,**","winRate":63.64,"pickRate":0.14,"variants":["TB,BP,PS,HC,CB","TB,BP,PS,HC","TB,BP,PS,HC,MJ,AE","TB,BP,PS,HC,AE","TB,BP,PS,HC,TT","TB,BP,PS,JB,SB,MJ","TB,BP,PS,JB,AE","TB,BP,PS,JB,SB,AE","TB,BP,PS,JB","TB,BP,PS,JB,MJ","TB,BP,PS,JB,SB","TB,BP,PS,JB,AE,MJ","TB,BP,PS,JB,SH","TB,BP,PS,JB,TT,MJ"],"items":["Tension Bow","Breaking Point","Poisoned Shiv","Situational Boots"]},{"key":"TB,TT,SB,*","winRate":57.14,"pickRate":0.14,"variants":["TB,TT,SB,SH,HC","TB,TT,SB,SH","TB,TT,SB,AE","TB,TT,SB,AE,JB","TB,TT,SB,AE,SH,WT","TB,TT,SB,AE,HC","TB,TT,SB,AE,BP,HC,SH,AE","TB,TT,SB,AE,MJ,JB,HC","TB,TT,SB,AE,BP,HC","TB,TT,SB,AE,PS,WT","TB,TT,SB,MJ,JB","TB,TT,SB,MJ"],"items":["Tension Bow","Tornado Trigger","Sorrowblade","Situational Defense"]},{"key":"TB,PS,AE,SB","winRate":47.62,"pickRate":0.14,"variants":["TB,PS,AE,SB,BP","TB,PS,AE,SB,SM,WT","TB,PS,AE,SB","TB,PS,AE,SB,JB","TB,PS,AE,SB,HC","TB,PS,AE,SB,TT,JB","TB,PS,AE,SB,HC,TT","TB,PS,AE,SB,WT","TB,PS,AE,SB,WT,BP","TB,PS,AE,SB,JB,BP","TB,PS,AE,SB,TE,FR"],"items":["Tension Bow","Poisoned Shiv","Aegis","Sorrowblade"]},{"key":"TB,BP,SB,PS","winRate":75,"pickRate":0.13,"variants":["TB,BP,SB,PS","TB,BP,SB,PS,AE,JB","TB,BP,SB,PS,HC","TB,BP,SB,PS,JB","TB,BP,SB,PS,JB,SH","TB,BP,SB,PS,AE","TB,BP,SB,PS,JB,MJ","TB,BP,SB,PS,NG,NG","TB,BP,SB,PS,MJ","TB,BP,SB,PS,HC,TT"],"items":["Tension Bow","Breaking Point","Sorrowblade","Poisoned Shiv"]},{"key":"TB,PS,SB,BP","winRate":75,"pickRate":0.13,"variants":["TB,PS,SB,BP","TB,PS,SB,BP,AE","TB,PS,SB,BP,JB,SH,TT,AE","TB,PS,SB,BP,AE,JB","TB,PS,SB,BP,JB,TT","TB,PS,SB,BP,AE,JB,MJ","TB,PS,SB,BP,HC","TB,PS,SB,BP,JB","TB,PS,SB,BP,MJ,HC"],"items":["Tension Bow","Poisoned Shiv","Sorrowblade","Breaking Point"]},{"key":"TB,SB,*,BS","winRate":70,"pickRate":0.13,"variants":["TB,SB,AE,BS,HC","TB,SB,AE,BS","TB,SB,AE,BS,JB","TB,SB,AE,BS,WT","TB,SB,AE,BS,MJ","TB,SB,AE,BS,AP,JB,BP","TB,SB,MJ,BS","TB,SB,MJ,BS,HC","TB,SB,MJ,BS,AE"],"items":["Tension Bow","Sorrowblade","Situational Defense","Bonesaw"]},{"key":"TB,*,SB,**","winRate":65,"pickRate":0.13,"variants":["TB,AE,SB,HC","TB,AE,SB,HC,TT","TB,AE,SB,HC,PS","TB,AE,SB,HC,BP","TB,AE,SB,JB,MJ","TB,AE,SB,JB,SS,TT","TB,AE,SB,JB,TT","TB,AE,SB,JB","TB,SH,SB,HC,TT,TT","TB,SH,SB,JB,BP","TB,MJ,SB,JB"],"items":["Tension Bow","Situational Defense","Sorrowblade","Situational Boots"]},{"key":"TB,PS,*,**","winRate":60,"pickRate":0.13,"variants":["TB,PS,AE,JB","TB,PS,AE,JB,MJ","TB,PS,AE,JB,SS","TB,PS,AE,JB,SB","TB,PS,SH,JB,SB","TB,PS,MJ,HC","TB,PS,AE,HC,BP,BS","TB,PS,AE,HC","TB,PS,AE,HC,SB","TB,PS,AE,HC,BP"],"items":["Tension Bow","Poisoned Shiv","Situational Defense","Situational Boots"]},{"key":"TB,**,BP,*","winRate":50,"pickRate":0.13,"variants":["TB,JB,BP,AE","TB,JB,BP,AE,MJ","TB,HC,BP,SH,SB","TB,HC,BP,AE,SB,MJ","TB,HC,BP,AE","TB,HC,BP,AE,MJ,SM,SB","TB,HC,BP,AE,MJ","TB,HC,BP,AE,SB"],"items":["Tension Bow","Situational Boots","Breaking Point","Situational Defense"]},{"key":"TB,**,SB,TT","winRate":84.21,"pickRate":0.12,"variants":["TB,JB,SB,TT","TB,JB,SB,TT,AE","TB,HC,SB,TT,AE,MJ","TB,HC,SB,TT","TB,HC,SB,TT,AE","TB,HC,SB,TT,TT,AE","TB,HC,SB,TT,PS","TB,HC,SB,TT,MJ"],"items":["Tension Bow","Situational Boots","Sorrowblade","Tornado Trigger"]},{"key":"TB,BP,TT,*","winRate":83.33,"pickRate":0.12,"variants":["TB,BP,TT,AE,JB,SB","TB,BP,TT,AE","TB,BP,TT,AE,JB","TB,BP,TT,AE,SB","TB,BP,TT,AE,JB,TT","TB,BP,TT,AE,SB,BS","TB,BP,TT,AE,FR","TB,BP,TT,MJ","TB,BP,TT,MJ,JB","TB,BP,TT,SH"],"items":["Tension Bow","Breaking Point","Tornado Trigger","Situational Defense"]},{"key":"SB,BP,BS,**","winRate":77.78,"pickRate":0.12,"variants":["SB,BP,BS,JB","SB,BP,BS,JB,MJ","SB,BP,BS,JB,TB,AE","SB,BP,BS,JB,AE","SB,BP,BS,HC","SB,BP,BS,HC,PS","SB,BP,BS,HC,AE,SB"],"items":["Sorrowblade","Breaking Point","Bonesaw","Situational Boots"]},{"key":"SG,CW,SF,BM","winRate":66.67,"pickRate":0.12,"variants":["SG,CW,SF,BM","SG,CW,SF,BM,JB,AE","SG,CW,SF,BM,HC,SH","SG,CW,SF,BM,HC,SG","SG,CW,SF,BM,HC","SG,CW,SF,BM,AE","SG,CW,SF,BM,HC,DE","SG,CW,SF,BM,JB,SG"],"items":["Shatterglass","Clockwork","Spellfire","Broken Myth"]},{"key":"SB,BP,*,*","winRate":61.11,"pickRate":0.12,"variants":["SB,BP,AE,AP","SB,BP,MJ,AE,BS","SB,BP,MJ,AE","SB,BP,MJ,AE,JB,SH,JB,PS","SB,BP,MJ,AE,HC,JB","SB,BP,AE,MJ","SB,BP,AE,MJ,JB","SB,BP,AE,MJ,PS","SB,BP,AE,MJ,WT"],"items":["Sorrowblade","Breaking Point","Situational Defense","Situational Defense"]},{"key":"TB,BP,**,TT","winRate":70.59,"pickRate":0.11,"variants":["TB,BP,HC,TT,SM,PS","TB,BP,HC,TT","TB,BP,HC,TT,TT,AE,SB,PS","TB,BP,JB,TT"],"items":["Tension Bow","Breaking Point","Situational Boots","Tornado Trigger"]},{"key":"PS,SB,BP,AE","winRate":64.71,"pickRate":0.11,"variants":["PS,SB,BP,AE,TT,JB","PS,SB,BP,AE,TT,JB,BS","PS,SB,BP,AE,HC","PS,SB,BP,AE,BS","PS,SB,BP,AE,BS,HC","PS,SB,BP,AE","PS,SB,BP,AE,MJ,HC","PS,SB,BP,AE,BS,JB"],"items":["Poisoned Shiv","Sorrowblade","Breaking Point","Aegis"]},{"key":"TB,*,**,SB","winRate":58.82,"pickRate":0.11,"variants":["TB,AE,HC,SB,BP,TB","TB,AE,HC,SB","TB,AE,HC,SB,PS","TB,AE,HC,SB,AP","TB,AE,JB,SB","TB,AE,JB,SB,MJ","TB,AE,JB,SB,BP","TB,AE,JB,SB,BS","TB,MJ,HC,SB"],"items":["Tension Bow","Situational Defense","Situational Boots","Sorrowblade"]},{"key":"TB,PS,AE,BP","winRate":56.25,"pickRate":0.1,"variants":["TB,PS,AE,BP,JB","TB,PS,AE,BP,MJ,JB,SB","TB,PS,AE,BP","TB,PS,AE,BP,JB,TT","TB,PS,AE,BP,TT,JB","TB,PS,AE,BP,JB,SB","TB,PS,AE,BP,HC,SB","TB,PS,AE,BP,SS,JB,SB,TT","TB,PS,AE,BP,HC"],"items":["Tension Bow","Poisoned Shiv","Aegis","Breaking Point"]},{"key":"TB,SB,BS,AE","winRate":43.75,"pickRate":0.1,"variants":["TB,SB,BS,AE","TB,SB,BS,AE,MJ","TB,SB,BS,AE,JB","TB,SB,BS,AE,JB,SS","TB,SB,BS,AE,JB,MJ","TB,SB,BS,AE,WT","TB,SB,BS,AE,HC,BP","TB,SB,BS,AE,JB,CB"],"items":["Tension Bow","Sorrowblade","Bonesaw","Aegis"]},{"key":"TB,BP,SS,AE","winRate":43.75,"pickRate":0.1,"variants":["TB,BP,SS,AE","TB,BP,SS,AE,SB","TB,BP,SS,AE,HC","TB,BP,SS,AE,JB","TB,BP,SS,AE,PS","TB,BP,SS,AE,HC,MJ,SB","TB,BP,SS,AE,JB,MJ","TB,BP,SS,AE,MJ,HC,SB","TB,BP,SS,AE,SB,HC"],"items":["Tension Bow","Breaking Point","Spellsword","Aegis"]},{"key":"TB,BP,**,PS","winRate":43.75,"pickRate":0.1,"variants":["TB,BP,HC,PS","TB,BP,HC,PS,BS,AE","TB,BP,HC,PS,CB","TB,BP,HC,PS,SB","TB,BP,HC,PS,TT,BS","TB,BP,HC,PS,TT,TT,SB","TB,BP,HC,PS,TT","TB,BP,HC,PS,AE","TB,BP,JB,PS,AE,SB","TB,BP,JB,PS","TB,BP,JB,PS,AE"],"items":["Tension Bow","Breaking Point","Situational Boots","Poisoned Shiv"]},{"key":"SB,BP,*,TB","winRate":37.5,"pickRate":0.1,"variants":["SB,BP,AE,TB","SB,BP,AE,TB,JB,PS","SB,BP,AE,TB,JB","SB,BP,AE,TB,TT","SB,BP,AE,TB,HC","SB,BP,SH,TB,AE","SB,BP,SH,TB,AE,SB","SB,BP,SH,TB","SB,BP,SH,TB,CB,AE","SB,BP,SH,TB,TB"],"items":["Sorrowblade","Breaking Point","Situational Defense","Tension Bow"]},{"key":"TB,SB,**,PS","winRate":73.33,"pickRate":0.1,"variants":["TB,SB,JB,PS,BS,MJ","TB,SB,JB,PS,BP","TB,SB,JB,PS,AE","TB,SB,JB,PS,MJ","TB,SB,JB,PS","TB,SB,HC,PS","TB,SB,HC,PS,AE","TB,SB,HC,PS,AE,TT","TB,SB,HC,PS,AP,BP","TB,SB,HC,PS,MJ"],"items":["Tension Bow","Sorrowblade","Situational Boots","Poisoned Shiv"]},{"key":"SB,BP,TT,AE","winRate":73.33,"pickRate":0.1,"variants":["SB,BP,TT,AE,JB,BS","SB,BP,TT,AE,WT","SB,BP,TT,AE","SB,BP,TT,AE,JB,HC","SB,BP,TT,AE,JB,WT","SB,BP,TT,AE,MJ,JB","SB,BP,TT,AE,JB","SB,BP,TT,AE,MJ","SB,BP,TT,AE,SM,JB"],"items":["Sorrowblade","Breaking Point","Tornado Trigger","Aegis"]},{"key":"TB,BP,SB,TT","winRate":66.67,"pickRate":0.1,"variants":["TB,BP,SB,TT","TB,BP,SB,TT,JB","TB,BP,SB,TT,AE","TB,BP,SB,TT,HC,AE","TB,BP,SB,TT,JB,AE","TB,BP,SB,TT,CB,WT","TB,BP,SB,TT,HC"],"items":["Tension Bow","Breaking Point","Sorrowblade","Tornado Trigger"]},{"key":"SB,BP,AE,PS","winRate":66.67,"pickRate":0.1,"variants":["SB,BP,AE,PS,JB","SB,BP,AE,PS,TB,JB","SB,BP,AE,PS,MJ,JB","SB,BP,AE,PS","SB,BP,AE,PS,MJ","SB,BP,AE,PS,TT","SB,BP,AE,PS,HC","SB,BP,AE,PS,JB,DE,CW","SB,BP,AE,PS,BS,JB","SB,BP,AE,PS,JB,SG,CW"],"items":["Sorrowblade","Breaking Point","Aegis","Poisoned Shiv"]},{"key":"SB,BP,AE,BS","winRate":40,"pickRate":0.1,"variants":["SB,BP,AE,BS,HC","SB,BP,AE,BS,JB","SB,BP,AE,BS","SB,BP,AE,BS,MJ","SB,BP,AE,BS,MJ,HC,WT"],"items":["Sorrowblade","Breaking Point","Aegis","Bonesaw"]},{"key":"SB,PS,**,BP","winRate":92.86,"pickRate":0.09,"variants":["SB,PS,HC,BP,MJ","SB,PS,HC,BP,AE","SB,PS,HC,BP","SB,PS,HC,BP,AE,SM","SB,PS,JB,BP,AE","SB,PS,JB,BP","SB,PS,JB,BP,BS","SB,PS,JB,BP,BS,AE"],"items":["Sorrowblade","Poisoned Shiv","Situational Boots","Breaking Point"]},{"key":"TB,TT,**,*","winRate":71.43,"pickRate":0.09,"variants":["TB,TT,JB,AE,SM","TB,TT,JB,AE","TB,TT,HC,AE","TB,TT,HC,AE,SB","TB,TT,HC,AE,BP","TB,TT,HC,AE,PS","TB,TT,HC,AE,PS,SB","TB,TT,HC,MJ"],"items":["Tension Bow","Tornado Trigger","Situational Boots","Situational Defense"]},{"key":"TB,TT,SB,**","winRate":71.43,"pickRate":0.09,"variants":["TB,TT,SB,JB","TB,TT,SB,JB,AE,TT","TB,TT,SB,JB,BP","TB,TT,SB,JB,AE","TB,TT,SB,HC,AE","TB,TT,SB,HC","TB,TT,SB,HC,AE,BP","TB,TT,SB,HC,TT,AE","TB,TT,SB,HC,AE,TT","TB,TT,SB,HC,MJ"],"items":["Tension Bow","Tornado Trigger","Sorrowblade","Situational Boots"]},{"key":"SB,BP,TB,AE","winRate":64.29,"pickRate":0.09,"variants":["SB,BP,TB,AE,JB","SB,BP,TB,AE,TT,WT","SB,BP,TB,AE","SB,BP,TB,AE,SS,JB","SB,BP,TB,AE,JB,MJ","SB,BP,TB,AE,HC,MJ"],"items":["Sorrowblade","Breaking Point","Tension Bow","Aegis"]},{"key":"TB,**,SB,PS","winRate":57.14,"pickRate":0.09,"variants":["TB,JB,SB,PS","TB,JB,SB,PS,AE","TB,JB,SB,PS,BP,SS","TB,JB,SB,PS,MJ,AE","TB,JB,SB,PS,BP","TB,HC,SB,PS,SB","TB,HC,SB,PS,BS","TB,HC,SB,PS","TB,HC,SB,PS,AE,AP,BP","TB,HC,SB,PS,AE"],"items":["Tension Bow","Situational Boots","Sorrowblade","Poisoned Shiv"]},{"key":"TB,SB,BP,WT","winRate":50,"pickRate":0.09,"variants":["TB,SB,BP,WT,MJ","TB,SB,BP,WT","TB,SB,BP,WT,AE,TT,TB","TB,SB,BP,WT,MJ,TT","TB,SB,BP,WT,AE","TB,SB,BP,WT,CB"],"items":["Tension Bow","Sorrowblade","Breaking Point","War Treads"]},{"key":"SB,BP,TT,**","winRate":84.62,"pickRate":0.08,"variants":["SB,BP,TT,JB","SB,BP,TT,JB,MJ","SB,BP,TT,JB,AE","SB,BP,TT,JB,SH","SB,BP,TT,HC,MJ","SB,BP,TT,HC"],"items":["Sorrowblade","Breaking Point","Tornado Trigger","Situational Boots"]},{"key":"TB,SB,TT,TT","winRate":69.23,"pickRate":0.08,"variants":["TB,SB,TT,TT","TB,SB,TT,TT,JB","TB,SB,TT,TT,CB,JB,WT","TB,SB,TT,TT,MJ","TB,SB,TT,TT,SB","TB,SB,TT,TT,HC","TB,SB,TT,TT,SS,WT","TB,SB,TT,TT,WT","TB,SB,TT,TT,AE"],"items":["Tension Bow","Sorrowblade","Tornado Trigger","Tornado Trigger"]},{"key":"TB,BP,AE,PS","winRate":69.23,"pickRate":0.08,"variants":["TB,BP,AE,PS","TB,BP,AE,PS,BS,JB","TB,BP,AE,PS,BS,WT","TB,BP,AE,PS,SB,HC","TB,BP,AE,PS,JB,SB","TB,BP,AE,PS,MJ"],"items":["Tension Bow","Breaking Point","Aegis","Poisoned Shiv"]},{"key":"TB,**,*,SB","winRate":61.54,"pickRate":0.08,"variants":["TB,JB,AE,SB","TB,JB,AE,SB,TT","TB,JB,AE,SB,BS,MJ","TB,HC,AE,SB","TB,HC,AE,SB,BP"],"items":["Tension Bow","Situational Boots","Situational Defense","Sorrowblade"]},{"key":"TB,SS,BP,AE","winRate":53.85,"pickRate":0.08,"variants":["TB,SS,BP,AE,MJ,JB,SB","TB,SS,BP,AE","TB,SS,BP,AE,JB","TB,SS,BP,AE,SB,BS,JB","TB,SS,BP,AE,SH,JB"],"items":["Tension Bow","Spellsword","Breaking Point","Aegis"]},{"key":"SB,BP,AE,TT","winRate":46.15,"pickRate":0.08,"variants":["SB,BP,AE,TT,JB","SB,BP,AE,TT,HC","SB,BP,AE,TT","SB,BP,AE,TT,AP","SB,BP,AE,TT,MJ"],"items":["Sorrowblade","Breaking Point","Aegis","Tornado Trigger"]},{"key":"SB,BP,PS,BS","winRate":81.82,"pickRate":0.07,"variants":["SB,BP,PS,BS,HC","SB,BP,PS,BS,AE","SB,BP,PS,BS","SB,BP,PS,BS,JB","SB,BP,PS,BS,AE,JB","SB,BP,PS,BS,AE,JB,TT","SB,BP,PS,BS,JB,AE"],"items":["Sorrowblade","Breaking Point","Poisoned Shiv","Bonesaw"]},{"key":"SB,TT,TT,SB","winRate":72.73,"pickRate":0.07,"variants":["SB,TT,TT,SB,HC,SM","SB,TT,TT,SB","SB,TT,TT,SB,EH,EH,EH","SB,TT,TT,SB,HC","SB,TT,TT,SB,SM"],"items":["Sorrowblade","Tornado Trigger","Tornado Trigger","Sorrowblade"]},{"key":"TB,**,*,BP","winRate":72.73,"pickRate":0.07,"variants":["TB,HC,AE,BP","TB,HC,AE,BP,PS","TB,HC,AE,BP,SB","TB,JB,AE,BP,SM,SS","TB,JB,AE,BP,SM,SB","TB,JB,AE,BP,SS,SM","TB,JB,AE,BP,PS,SB"],"items":["Tension Bow","Situational Boots","Situational Defense","Breaking Point"]},{"key":"TB,PS,BP,SB","winRate":63.64,"pickRate":0.07,"variants":["TB,PS,BP,SB,JB,AE,BS","TB,PS,BP,SB,JB","TB,PS,BP,SB","TB,PS,BP,SB,AE,HC","TB,PS,BP,SB,MJ","TB,PS,BP,SB,AE","TB,PS,BP,SB,JB,AE,SM","TB,PS,BP,SB,WT"],"items":["Tension Bow","Poisoned Shiv","Breaking Point","Sorrowblade"]},{"key":"SB,TT,BP,*","winRate":63.64,"pickRate":0.07,"variants":["SB,TT,BP,AE,JB","SB,TT,BP,AE","SB,TT,BP,AE,SM","SB,TT,BP,AE,SM,JB","SB,TT,BP,MJ,AE","SB,TT,BP,MJ,JB,AE","SB,TT,BP,MJ"],"items":["Sorrowblade","Tornado Trigger","Breaking Point","Situational Defense"]},{"key":"SB,TB,*,**","winRate":45.45,"pickRate":0.07,"variants":["SB,TB,AE,HC","SB,TB,MJ,JB","SB,TB,SH,JB,TT,BP,AE","SB,TB,SH,JB,TT","SB,TB,AE,JB","SB,TB,AE,JB,MJ","SB,TB,AE,JB,BP","SB,TB,AE,JB,SB"],"items":["Sorrowblade","Tension Bow","Situational Defense","Situational Boots"]},{"key":"TB,BP,SS,**","winRate":27.27,"pickRate":0.07,"variants":["TB,BP,SS,JB,AE","TB,BP,SS,JB,AE,TT","TB,BP,SS,JB,SH","TB,BP,SS,JB,SB","TB,BP,SS,JB,PS","TB,BP,SS,JB","TB,BP,SS,JB,AE,SB","TB,BP,SS,HC,AE","TB,BP,SS,HC","TB,BP,SS,HC,BS"],"items":["Tension Bow","Breaking Point","Spellsword","Situational Boots"]}],"categorySkills":[{"key":"acb","winRate":56.37,"pickRate":54.86},{"key":"abc","winRate":53.72,"pickRate":7.74},{"key":"bca","winRate":59.19,"pickRate":1.44}],"skills":[{"key":"a,b,a,a,b,c,a,a,c,b,b,c","category":"acb","winRate":56.73,"pickRate":43.59},{"key":"a,a,b,a,b,c,a,a,c,b,b,c","category":"acb","winRate":54.78,"pickRate":4.07},{"key":"a,b,a,a,b,c,a,a,b,b,b,c","category":"abc","winRate":53.92,"pickRate":3.8},{"key":"a,b,a,a,b,c,a,a,c,b,b,b","category":"abc","winRate":53.51,"pickRate":3.14},{"key":"b,a,a,a,b,c,a,a,c,b,b,c","category":"acb","winRate":55.98,"pickRate":2.38},{"key":"a,b,a,a,b,c,a,a,b,c,b,c","category":"acb","winRate":50,"pickRate":1.4},{"key":"a,b,a,b,a,c,a,a,c,b,b,c","category":"acb","winRate":56.55,"pickRate":0.94},{"key":"a,b,b,a,a,c,a,a,c,b,b,c","category":"acb","winRate":56.35,"pickRate":0.82},{"key":"b,a,b,b,a,c,b,b,c,a,a,c","category":"bca","winRate":67.21,"pickRate":0.79},{"key":"a,b,a,a,b,c,a,b,c,a,b,c","category":"acb","winRate":56.14,"pickRate":0.74},{"key":"a,b,b,b,a,c,b,b,c,a,a,c","category":"bca","winRate":49.5,"pickRate":0.65},{"key":"a,b,a,a,b,c,b,a,c,a,b,c","category":"acb","winRate":51.65,"pickRate":0.59},{"key":"a,b,a,a,b,c,a,a,b,c,b,b","category":"abc","winRate":58.11,"pickRate":0.48},{"key":"a,b,a,a,c,a,b,a,c,b,b,c","category":"acb","winRate":66.67,"pickRate":0.33},{"key":"a,b,a,a,b,c,a,a,b,b,c,b","category":"abc","winRate":47.06,"pickRate":0.33}]}