{"name":"Koshka","winRate":52.28,"pickRate":27.5,"banRate":23.96,"stats":[{"name":"goldPerMin","stats":606.78,"rank":5,"total":38},{"name":"killsPerGame","stats":7.38,"rank":1,"total":38},{"name":"deathsPerGame","stats":5.16,"rank":7,"total":38},{"name":"assistsPerGame","stats":5.59,"rank":23,"total":38},{"name":"farmPerGame","stats":50.64,"rank":25,"total":38},{"name":"damagePerGame","stats":45739.87,"rank":16,"total":38},{"name":"healingPerGame","stats":8801.54,"rank":27,"total":38},{"name":"kda","stats":2.51,"rank":9,"total":38}],"roles":[{"key":"Carry","winRate":54.53,"pickRate":23.94},{"key":"Jungler","winRate":52.31,"pickRate":70.23},{"key":"Captain","winRate":42.78,"pickRate":5.83}],"durations":[{"key":"10","winRate":50.77,"pickRate":4.21},{"key":"20","winRate":53.04,"pickRate":46.91},{"key":"30","winRate":51.69,"pickRate":46.13},{"key":"40","winRate":51.81,"pickRate":2.69},{"key":"50","winRate":50,"pickRate":0.06}],"playingAgainst":[{"key":"Adagio","winRate":51.02,"pickRate":12.76},{"key":"Alpha","winRate":48.68,"pickRate":9.78},{"key":"Ardan","winRate":52.03,"pickRate":27.15},{"key":"Baptiste","winRate":53.45,"pickRate":13.15},{"key":"Baron","winRate":58.12,"pickRate":8.97},{"key":"Blackfeather","winRate":60.04,"pickRate":17.75},{"key":"Catherine","winRate":50.3,"pickRate":16.16},{"key":"Celeste","winRate":50.34,"pickRate":24},{"key":"Churnwalker","winRate":56.33,"pickRate":5.12},{"key":"Fortress","winRate":46.34,"pickRate":11.95},{"key":"Glaive","winRate":57.27,"pickRate":14.71},{"key":"Grace","winRate":44.47,"pickRate":13.48},{"key":"Grumpjaw","winRate":54.51,"pickRate":9.33},{"key":"Gwen","winRate":50.24,"pickRate":27.15},{"key":"Idris","winRate":53.93,"pickRate":22.64},{"key":"Joule","winRate":54.04,"pickRate":10.43},{"key":"Kestrel","winRate":52.55,"pickRate":20.96},{"key":"Krul","winRate":48.06,"pickRate":11.66},{"key":"Lance","winRate":56.17,"pickRate":7.61},{"key":"Lyra","winRate":51.06,"pickRate":12.18},{"key":"Ozo","winRate":55.28,"pickRate":3.98},{"key":"Petal","winRate":52.99,"pickRate":4.34},{"key":"Phinn","winRate":49.53,"pickRate":3.47},{"key":"Reim","winRate":49.3,"pickRate":4.6},{"key":"Reza","winRate":52.08,"pickRate":11.69},{"key":"Ringo","winRate":54.21,"pickRate":20.8},{"key":"Rona","winRate":49.47,"pickRate":21.22},{"key":"SAW","winRate":53.63,"pickRate":9.36},{"key":"Samuel","winRate":51.76,"pickRate":20.21},{"key":"Skaarf","winRate":51.84,"pickRate":13.18},{"key":"Skye","winRate":62.09,"pickRate":13.93},{"key":"Taka","winRate":53.67,"pickRate":9.72},{"key":"Tony","winRate":48.4,"pickRate":13.18},{"key":"Varya","winRate":48.1,"pickRate":13.67},{"key":"Vox","winRate":51.75,"pickRate":32.43},{"key":"Flicker","winRate":51.47,"pickRate":4.41},{"key":"Lorelai","winRate":64.77,"pickRate":2.85}],"playingWith":[{"key":"Adagio","winRate":54.52,"pickRate":10.4},{"key":"Alpha","winRate":52.03,"pickRate":4.79},{"key":"Ardan","winRate":54.96,"pickRate":25.82},{"key":"Baptiste","winRate":48.4,"pickRate":7.09},{"key":"Baron","winRate":45,"pickRate":8.42},{"key":"Blackfeather","winRate":45.99,"pickRate":12.54},{"key":"Catherine","winRate":54.28,"pickRate":14.38},{"key":"Celeste","winRate":53.41,"pickRate":20.93},{"key":"Flicker","winRate":51.54,"pickRate":4.21},{"key":"Fortress","winRate":58.15,"pickRate":7.35},{"key":"Glaive","winRate":51.18,"pickRate":9.62},{"key":"Grace","winRate":55.88,"pickRate":13.51},{"key":"Grumpjaw","winRate":54.74,"pickRate":4.44},{"key":"Gwen","winRate":51.22,"pickRate":29.15},{"key":"Idris","winRate":51.49,"pickRate":18.5},{"key":"Joule","winRate":50.88,"pickRate":9.23},{"key":"Kestrel","winRate":54.98,"pickRate":16.91},{"key":"Krul","winRate":56.57,"pickRate":3.21},{"key":"Lorelai","winRate":52.24,"pickRate":2.17},{"key":"Lyra","winRate":52.38,"pickRate":10.88},{"key":"Petal","winRate":49.32,"pickRate":2.36},{"key":"Phinn","winRate":42.74,"pickRate":3.79},{"key":"Reim","winRate":37.29,"pickRate":1.91},{"key":"Reza","winRate":53.55,"pickRate":5.02},{"key":"Ringo","winRate":49.78,"pickRate":21.74},{"key":"Rona","winRate":58.24,"pickRate":14.74},{"key":"SAW","winRate":45.57,"pickRate":10.24},{"key":"Samuel","winRate":57.56,"pickRate":15.42},{"key":"Skaarf","winRate":53.09,"pickRate":10.5},{"key":"Skye","winRate":47.79,"pickRate":13.22},{"key":"Taka","winRate":49.35,"pickRate":2.49},{"key":"Tony","winRate":54.07,"pickRate":8.75},{"key":"Varya","winRate":54.43,"pickRate":10.59},{"key":"Vox","winRate":53.73,"pickRate":32.98},{"key":"Lance","winRate":43.54,"pickRate":6.77},{"key":"Churnwalker","winRate":50.36,"pickRate":4.44},{"key":"Ozo","winRate":47.83,"pickRate":1.49}],"builds":[{"key":"AS,DE,BM,AE","winRate":56.85,"pickRate":4.73,"variants":["AS,DE,BM,AE","AS,DE,BM,AE,MJ,JB","AS,DE,BM,AE,AP,CB,FR","AS,DE,BM,AE,JB","AS,DE,BM,AE,HC,MJ","AS,DE,BM,AE,AP","AS,DE,BM,AE,JB,MJ","AS,DE,BM,AE,MJ","AS,DE,BM,AE,SF","AS,DE,BM,AE,MJ,JB,JB","AS,DE,BM,AE,AP,JB","AS,DE,BM,AE,SG,JB","AS,DE,BM,AE,JB,CW","AS,DE,BM,AE,SG,AP,JB","AS,DE,BM,AE,CW,HC","AS,DE,BM,AE,CW","AS,DE,BM,AE,MJ,HC","AS,DE,BM,AE,MJ,JB,WT","AS,DE,BM,AE,HC,SG","AS,DE,BM,AE,JB,BM","AS,DE,BM,AE,WT","AS,DE,BM,AE,AP,HC"],"items":["Aftershock","Dragon's Eye","Broken Myth","Aegis"]},{"key":"AS,BM,*,*","winRate":52.69,"pickRate":3.01,"variants":["AS,BM,AE,MJ,HC,SG,HC","AS,BM,AE,MJ","AS,BM,AE,MJ,SF,JB","AS,BM,AE,MJ,JB,SF","AS,BM,AE,MJ,JB,DE","AS,BM,AE,MJ,SG","AS,BM,AE,MJ,CW","AS,BM,AE,MJ,JB","AS,BM,AE,MJ,DE","AS,BM,AE,MJ,WT","AS,BM,AE,MJ,SF","AS,BM,AE,MJ,HC","AS,BM,AE,MJ,DE,JB","AS,BM,AE,MJ,HC,DE","AS,BM,AE,AP,CW","AS,BM,AE,AP","AS,BM,AE,AP,HC,SF","AS,BM,AE,AP,JB","AS,BM,AE,AP,SF","AS,BM,AE,AP,JB,CW","AS,BM,AE,AP,WT","AS,BM,AE,AP,HC","AS,BM,AE,AP,DE","AS,BM,AE,AP,SF,JB","AS,BM,AP,AE,HC","AS,BM,AP,AE,JB","AS,BM,AP,AE","AS,BM,AP,AE,DE","AS,BM,AP,AE,WT","AS,BM,AP,AE,WT,FR,SG,WT","AS,BM,MJ,AE","AS,BM,MJ,AE,HC","AS,BM,MJ,AE,DE,HC","AS,BM,MJ,AE,HC,SG","AS,BM,MJ,AE,SF","AS,BM,SH,AE,BM","AS,BM,AP,MJ"],"items":["Aftershock","Broken Myth","Situational Defense","Situational Defense"]},{"key":"AS,DE,AE,BM","winRate":54.29,"pickRate":2.27,"variants":["AS,DE,AE,BM","AS,DE,AE,BM,HC,AP","AS,DE,AE,BM,MJ,JB","AS,DE,AE,BM,MJ,HC","AS,DE,AE,BM,AP","AS,DE,AE,BM,HC,MJ","AS,DE,AE,BM,WT","AS,DE,AE,BM,MJ,WT","AS,DE,AE,BM,MJ","AS,DE,AE,BM,HC","AS,DE,AE,BM,JB,SG","AS,DE,AE,BM,HC,SC","AS,DE,AE,BM,CW","AS,DE,AE,BM,JB","AS,DE,AE,BM,JB,HC"],"items":["Aftershock","Dragon's Eye","Aegis","Broken Myth"]},{"key":"AS,DE,*,*","winRate":57.63,"pickRate":1.91,"variants":["AS,DE,AE,AP","AS,DE,AE,AP,HC","AS,DE,AE,AP,BM,HC","AS,DE,AE,AP,BM","AS,DE,AE,AP,BM,JB","AS,DE,AE,AP,JB,BM","AS,DE,AE,AP,WT,BM","AS,DE,AE,AP,HC,BM","AS,DE,AE,MJ,BM,HC","AS,DE,AE,MJ,BM","AS,DE,AE,MJ,JB","AS,DE,AE,MJ","AS,DE,AE,MJ,BM,JB,SG","AS,DE,AE,MJ,BM,JB","AS,DE,AE,MJ,BM,WT","AS,DE,AE,MJ,HC,BM","AS,DE,AE,MJ,HC","AS,DE,AP,AE","AS,DE,AP,AE,BM","AS,DE,AP,AE,JB","AS,DE,AP,AE,JB,BM","AS,DE,AP,AE,HC","AS,DE,AP,AE,WT","AS,DE,MJ,AE,BM,HC","AS,DE,MJ,AE,JB","AS,DE,MJ,AE,JB,BM","AS,DE,MJ,AE,HC","AS,DE,MJ,AE,CW","AS,DE,AE,SH,SC,JB","AS,DE,AE,AE,AE"],"items":["Aftershock","Dragon's Eye","Situational Defense","Situational Defense"]},{"key":"AS,BM,AE,DE","winRate":66.67,"pickRate":1.26,"variants":["AS,BM,AE,DE,HC","AS,BM,AE,DE","AS,BM,AE,DE,SC","AS,BM,AE,DE,AP","AS,BM,AE,DE,HC,MJ","AS,BM,AE,DE,MJ","AS,BM,AE,DE,CW,JB","AS,BM,AE,DE,JB","AS,BM,AE,DE,AP,JB","AS,BM,AE,DE,JB,FR","AS,BM,AE,DE,AP,WT","AS,BM,AE,DE,HC,SF","AS,BM,AE,DE,MJ,HC"],"items":["Aftershock","Broken Myth","Aegis","Dragon's Eye"]},{"key":"AS,SF,BM,*","winRate":71.05,"pickRate":1.23,"variants":["AS,SF,BM,MJ,AE","AS,SF,BM,MJ","AS,SF,BM,MJ,JB","AS,SF,BM,MJ,AE,WT,FR","AS,SF,BM,MJ,AE,WT","AS,SF,BM,AP","AS,SF,BM,AP,DE","AS,SF,BM,AP,CW,HC","AS,SF,BM,AP,HC","AS,SF,BM,AP,AE","AS,SF,BM,AE","AS,SF,BM,AE,HC","AS,SF,BM,AE,AP","AS,SF,BM,AE,FB","AS,SF,BM,AE,HC,AP","AS,SF,BM,AE,MJ","AS,SF,BM,AE,MJ,HC"],"items":["Aftershock","Spellfire","Broken Myth","Situational Defense"]},{"key":"AS,BM,*,**","winRate":64.86,"pickRate":1.2,"variants":["AS,BM,AE,JB","AS,BM,AE,JB,CW","AS,BM,AE,JB,WT","AS,BM,AE,JB,DE","AS,BM,AE,JB,SF,MJ","AS,BM,AE,JB,AP,CW","AS,BM,AE,JB,MJ","AS,BM,AE,JB,DE,MJ,JB","AS,BM,AE,HC,CW","AS,BM,AE,HC,AP","AS,BM,AE,HC","AS,BM,AE,HC,SF,AP","AS,BM,AE,HC,DE,MJ","AS,BM,AE,HC,SF","AS,BM,AE,HC,SG","AS,BM,AE,HC,MJ,DE","AS,BM,AE,HC,AP,HC","AS,BM,AE,HC,MJ","AS,BM,AE,HC,SF,MJ","AS,BM,MJ,HC,SG,AE","AS,BM,MJ,JB","AS,BM,AP,JB","AS,BM,AP,JB,AE","AS,BM,AP,HC,SF,AE","AS,BM,AP,HC,FR,DE","AS,BM,AP,HC","AS,BM,SH,JB"],"items":["Aftershock","Broken Myth","Situational Defense","Situational Boots"]},{"key":"AS,DE,*,**","winRate":72.22,"pickRate":1.17,"variants":["AS,DE,MJ,JB,BM","AS,DE,AE,HC,AP","AS,DE,AE,HC,BM,MJ","AS,DE,AE,HC","AS,DE,AE,HC,BM","AS,DE,AE,HC,MJ,BM","AS,DE,AE,HC,FR,BM","AS,DE,AE,HC,MJ","AS,DE,AE,HC,SH","AS,DE,AE,HC,AP,FR","AS,DE,AE,JB,AP,BM","AS,DE,AE,JB,BM","AS,DE,AE,JB","AS,DE,AP,JB,AE","AS,DE,SH,JB,BM","AS,DE,AP,HC,BM","AS,DE,AP,HC,AE","AS,DE,MJ,HC,BM"],"items":["Aftershock","Dragon's Eye","Situational Defense","Situational Boots"]},{"key":"AS,SF,*,BM","winRate":59.38,"pickRate":1.04,"variants":["AS,SF,MJ,BM","AS,SF,MJ,BM,AE","AS,SF,AE,BM","AS,SF,AE,BM,HC,AP","AS,SF,AE,BM,HC","AS,SF,AE,BM,MJ","AS,SF,AE,BM,AP,WT","AS,SF,AE,BM,AP","AS,SF,AE,BM,HC,AP,HC,HC","AS,SF,AE,BM,MJ,HC","AS,SF,AE,BM,JB,AP","AS,SF,AE,BM,MJ,JB","AS,SF,AP,BM,HC","AS,SF,AP,BM,CB","AS,SF,AP,BM,AE"],"items":["Aftershock","Spellfire","Situational Defense","Broken Myth"]},{"key":"SG,CW,BM,AE","winRate":41.94,"pickRate":1,"variants":["SG,CW,BM,AE,DE","SG,CW,BM,AE","SG,CW,BM,AE,DE,JB","SG,CW,BM,AE,DE,JB,SG","SG,CW,BM,AE,JB,DE","SG,CW,BM,AE,AS","SG,CW,BM,AE,MJ"],"items":["Shatterglass","Clockwork","Broken Myth","Aegis"]},{"key":"AS,SG,*,*","winRate":44.44,"pickRate":0.87,"variants":["AS,SG,MJ,AE,HC","AS,SG,MJ,AE,BM,HC","AS,SG,MJ,AE,JB","AS,SG,AE,AP","AS,SG,AE,AP,BM","AS,SG,AE,AP,HC,BM","AS,SG,AE,MJ,HC","AS,SG,AE,MJ","AS,SG,AE,MJ,BM,HC","AS,SG,AE,MJ,SG","AS,SG,AP,AE","AS,SG,AP,AE,BM"],"items":["Aftershock","Shatterglass","Situational Defense","Situational Defense"]},{"key":"AS,SF,*,*","winRate":48,"pickRate":0.81,"variants":["AS,SF,AE,MJ","AS,SF,AE,MJ,BM,HC","AS,SF,AE,MJ,WT,BM","AS,SF,AE,MJ,WT","AS,SF,AE,MJ,BM","AS,SF,MJ,AE,BM,JB","AS,SF,MJ,AE","AS,SF,MJ,AE,HC","AS,SF,AP,AE,BM","AS,SF,AP,AE","AS,SF,AP,AE,BM,WT","AS,SF,AP,AE,JB,EH","AS,SF,AP,AE,HC,DE","AS,SF,AE,AP","AS,SF,AE,AP,WT,DE"],"items":["Aftershock","Spellfire","Situational Defense","Situational Defense"]},{"key":"AS,BM,*,SF","winRate":70.83,"pickRate":0.78,"variants":["AS,BM,AE,SF","AS,BM,AE,SF,WT","AS,BM,AE,SF,HC,MJ","AS,BM,AE,SF,MJ,HC","AS,BM,AE,SF,AP","AS,BM,AE,SF,HC","AS,BM,AE,SF,WT,MJ","AS,BM,AP,SF,HC","AS,BM,AP,SF,AE","AS,BM,AP,SF,CB,WT","AS,BM,MJ,SF,AE,JB","AS,BM,MJ,SF,AE","AS,BM,MJ,SF,JB,HC"],"items":["Aftershock","Broken Myth","Situational Defense","Spellfire"]},{"key":"AS,BM,**,*","winRate":54.17,"pickRate":0.78,"variants":["AS,BM,HC,AP,AE,DE","AS,BM,JB,MJ","AS,BM,JB,AE,MJ","AS,BM,JB,AE","AS,BM,HC,MJ,AE","AS,BM,HC,MJ","AS,BM,HC,MJ,SF","AS,BM,HC,MJ,AE,DE","AS,BM,HC,MJ,DE,AE","AS,BM,HC,AE","AS,BM,HC,AE,DE,SG","AS,BM,HC,AE,MJ","AS,BM,HC,AE,SG","AS,BM,HC,AE,CW,AP,SG","AS,BM,HC,AE,SG,MJ","AS,BM,HC,AE,SG,CW"],"items":["Aftershock","Broken Myth","Situational Boots","Situational Defense"]},{"key":"AS,BM,SF,AE","winRate":59.09,"pickRate":0.71,"variants":["AS,BM,SF,AE,FR","AS,BM,SF,AE,MJ","AS,BM,SF,AE,HC","AS,BM,SF,AE,JB,CW","AS,BM,SF,AE,AP","AS,BM,SF,AE,DE,HC","AS,BM,SF,AE","AS,BM,SF,AE,JB","AS,BM,SF,AE,HC,DE","AS,BM,SF,AE,HC,MJ","AS,BM,SF,AE,HC,AP"],"items":["Aftershock","Broken Myth","Spellfire","Aegis"]},{"key":"AS,BM,DE,AE","winRate":66.67,"pickRate":0.68,"variants":["AS,BM,DE,AE","AS,BM,DE,AE,MJ","AS,BM,DE,AE,HC","AS,BM,DE,AE,HC,SF","AS,BM,DE,AE,MJ,HC,SG","AS,BM,DE,AE,HC,MJ","AS,BM,DE,AE,AP"],"items":["Aftershock","Broken Myth","Dragon's Eye","Aegis"]},{"key":"AS,BM,SG,*","winRate":66.67,"pickRate":0.68,"variants":["AS,BM,SG,MJ","AS,BM,SG,MJ,AE","AS,BM,SG,AE,WT","AS,BM,SG,AE","AS,BM,SG,AE,MJ","AS,BM,SG,AE,DE","AS,BM,SG,AE,HC,MJ","AS,BM,SG,AE,AP,WT","AS,BM,SG,AE,AP","AS,BM,SG,AE,HC","AS,BM,SG,AP,WT","AS,BM,SG,AP,HC,AE,DE"],"items":["Aftershock","Broken Myth","Shatterglass","Situational Defense"]},{"key":"AS,SG,AE,BM","winRate":75,"pickRate":0.65,"variants":["AS,SG,AE,BM,HC,MJ","AS,SG,AE,BM,MJ,HC","AS,SG,AE,BM,AP,HC","AS,SG,AE,BM","AS,SG,AE,BM,MJ,WT","AS,SG,AE,BM,SF","AS,SG,AE,BM,HC","AS,SG,AE,BM,CW,HC","AS,SG,AE,BM,JB,CW,FR"],"items":["Aftershock","Shatterglass","Aegis","Broken Myth"]},{"key":"AS,*,BM,**","winRate":55,"pickRate":0.65,"variants":["AS,AP,BM,HC,AE,SG","AS,AP,BM,HC,AE","AS,AP,BM,HC,DE,AE","AS,AE,BM,JB,SH,MJ","AS,AE,BM,JB","AS,AE,BM,HC,MJ","AS,AE,BM,HC","AS,AE,BM,HC,MJ,DE","AS,AE,BM,HC,AP","AS,AE,BM,HC,SF","AS,AE,BM,HC,DE,MJ","AS,AE,BM,HC,AP,DE","AS,AP,BM,JB,AE","AS,SH,BM,HC,SG"],"items":["Aftershock","Situational Defense","Broken Myth","Situational Boots"]},{"key":"AS,DE,**,*","winRate":73.68,"pickRate":0.62,"variants":["AS,DE,HC,AE,AP","AS,DE,HC,AE","AS,DE,HC,AE,BM,MJ","AS,DE,HC,AE,AP,CW","AS,DE,HC,AE,AP,BM","AS,DE,HC,AE,BM","AS,DE,HC,AE,JB","AS,DE,HC,AE,MJ,BM","AS,DE,HC,AE,MJ","AS,DE,HC,AP","AS,DE,HC,AP,BM","AS,DE,JB,AE","AS,DE,HC,MJ"],"items":["Aftershock","Dragon's Eye","Situational Boots","Situational Defense"]},{"key":"AS,*,DE,*","winRate":31.58,"pickRate":0.62,"variants":["AS,AP,DE,AE","AS,AP,DE,AE,HC","AS,AE,DE,MJ","AS,AE,DE,MJ,WT","AS,AE,DE,MJ,JB,BM","AS,AE,DE,MJ,HC","AS,AE,DE,MJ,WT,BM","AS,AE,DE,MJ,BM,HC,CB","AS,AE,DE,AP","AS,AE,DE,AP,FR","AS,MJ,DE,AE","AS,AE,DE,SH"],"items":["Aftershock","Situational Defense","Dragon's Eye","Situational Defense"]},{"key":"SG,SF,AS,BM","winRate":77.78,"pickRate":0.58,"variants":["SG,SF,AS,BM,AE","SG,SF,AS,BM,AE,HC","SG,SF,AS,BM","SG,SF,AS,BM,AE,SG","SG,SF,AS,BM,HC","SG,SF,AS,BM,HC,AE,MJ","SG,SF,AS,BM,SC","SG,SF,AS,BM,AE,MJ"],"items":["Shatterglass","Spellfire","Aftershock","Broken Myth"]},{"key":"AS,BM,AE,SG","winRate":52.94,"pickRate":0.55,"variants":["AS,BM,AE,SG,HC","AS,BM,AE,SG,JB","AS,BM,AE,SG,MJ,HC","AS,BM,AE,SG,SG","AS,BM,AE,SG","AS,BM,AE,SG,MJ","AS,BM,AE,SG,HC,MJ","AS,BM,AE,SG,AP"],"items":["Aftershock","Broken Myth","Aegis","Shatterglass"]},{"key":"AS,DE,BM,**","winRate":75,"pickRate":0.52,"variants":["AS,DE,BM,HC,AE,MJ","AS,DE,BM,HC","AS,DE,BM,HC,AE","AS,DE,BM,JB","AS,DE,BM,JB,AE,CW","AS,DE,BM,JB,AE,MJ","AS,DE,BM,JB,AE"],"items":["Aftershock","Dragon's Eye","Broken Myth","Situational Boots"]},{"key":"AS,SG,BM,*","winRate":68.75,"pickRate":0.52,"variants":["AS,SG,BM,AE,SG,HC","AS,SG,BM,AE","AS,SG,BM,AE,SH,JB","AS,SG,BM,AE,HC","AS,SG,BM,AE,MJ,WT","AS,SG,BM,AE,DE,WT","AS,SG,BM,AE,MJ","AS,SG,BM,AE,JB","AS,SG,BM,AE,DE","AS,SG,BM,AP","AS,SG,BM,MJ","AS,SG,BM,MJ,AE","AS,SG,BM,SH,AE,JB"],"items":["Aftershock","Shatterglass","Broken Myth","Situational Defense"]},{"key":"AS,*,BM,*","winRate":62.5,"pickRate":0.52,"variants":["AS,AE,BM,MJ,SF,WT","AS,AE,BM,MJ","AS,MJ,BM,AE","AS,MJ,BM,AE,DE","AS,AE,BM,AP,DE,HC","AS,AE,BM,AP,HC","AS,AE,BM,AP","AS,AP,BM,AE,HC","AS,AP,BM,AE"],"items":["Aftershock","Situational Defense","Broken Myth","Situational Defense"]},{"key":"AS,DE,**,BM","winRate":73.33,"pickRate":0.49,"variants":["AS,DE,HC,BM,AE","AS,DE,HC,BM","AS,DE,HC,BM,AE,AP","AS,DE,HC,BM,AE,AP,SG,CW","AS,DE,HC,BM,AE,MJ","AS,DE,JB,BM,AE,MJ","AS,DE,JB,BM,AE","AS,DE,JB,BM"],"items":["Aftershock","Dragon's Eye","Situational Boots","Broken Myth"]},{"key":"AS,SG,*,**","winRate":78.57,"pickRate":0.45,"variants":["AS,SG,AP,HC","AS,SG,MJ,HC,AE","AS,SG,AE,HC,BM,MJ","AS,SG,AE,HC","AS,SG,AE,HC,AP,BM","AS,SG,AE,HC,BM","AS,SG,AE,JB"],"items":["Aftershock","Shatterglass","Situational Defense","Situational Boots"]},{"key":"AS,SF,BM,HC","winRate":64.29,"pickRate":0.45,"variants":["AS,SF,BM,HC,AE,AP","AS,SF,BM,HC,AE,CW","AS,SF,BM,HC,FB","AS,SF,BM,HC,AP,AE","AS,SF,BM,HC,DE","AS,SF,BM,HC","AS,SF,BM,HC,AE","AS,SF,BM,HC,AE,MJ","AS,SF,BM,HC,MJ","AS,SF,BM,HC,AE,MJ,HC"],"items":["Aftershock","Spellfire","Broken Myth","Halcyon Chargers"]},{"key":"AS,SG,**,BM","winRate":69.23,"pickRate":0.42,"variants":["AS,SG,HC,BM","AS,SG,HC,BM,AE","AS,SG,HC,BM,SH","AS,SG,HC,BM,AE,MJ","AS,SG,JB,BM","AS,SG,JB,BM,AP,AE","AS,SG,JB,BM,AE,DE"],"items":["Aftershock","Shatterglass","Situational Boots","Broken Myth"]},{"key":"AS,SF,*,**","winRate":61.54,"pickRate":0.42,"variants":["AS,SF,AE,HC,BM,CB","AS,SF,AE,HC,BM","AS,SF,AE,HC","AS,SF,AE,JB"],"items":["Aftershock","Spellfire","Situational Defense","Situational Boots"]},{"key":"AS,SG,BM,**","winRate":90.91,"pickRate":0.36,"variants":["AS,SG,BM,HC,AE,CW","AS,SG,BM,HC","AS,SG,BM,HC,MJ","AS,SG,BM,HC,SF,AE","AS,SG,BM,HC,MJ,AE","AS,SG,BM,JB,DE,CB","AS,SG,BM,JB,AE","AS,SG,BM,JB,AP,CW"],"items":["Aftershock","Shatterglass","Broken Myth","Situational Boots"]},{"key":"AS,*,*,BM","winRate":54.55,"pickRate":0.36,"variants":["AS,AP,AE,BM","AS,AP,AE,BM,HC,CW","AS,AP,AE,BM,JB","AS,AE,MJ,BM","AS,AE,MJ,BM,HC,FR","AS,AE,MJ,BM,SF","AS,MJ,AE,BM,AP","AS,MJ,AE,BM,HC,FR","AS,AE,AP,BM,DE"],"items":["Aftershock","Situational Defense","Situational Defense","Broken Myth"]},{"key":"AS,SF,**,*","winRate":54.55,"pickRate":0.36,"variants":["AS,SF,HC,AP,CB","AS,SF,HC,AP,FR","AS,SF,HC,AP,BM,AE","AS,SF,HC,AE,BM","AS,SF,HC,AE","AS,SF,JB,AE,MJ,SG","AS,SF,JB,AP","AS,SF,HC,MJ"],"items":["Aftershock","Spellfire","Situational Boots","Situational Defense"]},{"key":"SG,AS,AE,BM","winRate":45.45,"pickRate":0.36,"variants":["SG,AS,AE,BM,HC,DE","SG,AS,AE,BM","SG,AS,AE,BM,SF","SG,AS,AE,BM,HC,MJ","SG,AS,AE,BM,JB,MJ","SG,AS,AE,BM,MJ","SG,AS,AE,BM,HC"],"items":["Shatterglass","Aftershock","Aegis","Broken Myth"]}],"skills":[{"key":"b,a,b,b,a,c,b,b,a,a,a,c","category":"bac","winRate":62.26,"pickRate":25.75},{"key":"b,a,b,b,a,c,b,b,c,a,a,c","category":"bca","winRate":55.73,"pickRate":12.44},{"key":"b,a,b,b,a,c,b,b,c,a,a,a","category":"bac","winRate":59.17,"pickRate":10.95}]}