{"name":"Reim","winRate":49.66,"pickRate":5.37,"banRate":0.23,"stats":[{"name":"goldPerMin","stats":548.03,"rank":30,"total":43},{"name":"killsPerGame","stats":4.65,"rank":26,"total":43},{"name":"deathsPerGame","stats":5.48,"rank":40,"total":43},{"name":"assistsPerGame","stats":6.57,"rank":17,"total":43},{"name":"farmPerGame","stats":55.98,"rank":27,"total":43},{"name":"damagePerGame","stats":47676.58,"rank":23,"total":43},{"name":"healingPerGame","stats":11163.53,"rank":22,"total":43},{"name":"kda","stats":2.05,"rank":40,"total":43}],"roles":[{"key":"Captain","winRate":41.33,"pickRate":5.67},{"key":"Carry","winRate":48.29,"pickRate":33.18},{"key":"Jungler","winRate":51.17,"pickRate":61.15}],"durations":[{"key":"10","winRate":53.73,"pickRate":5.06},{"key":"20","winRate":48.81,"pickRate":35},{"key":"30","winRate":50.64,"pickRate":52.99},{"key":"40","winRate":43.48,"pickRate":6.95}],"playingAgainst":[{"key":"Adagio","winRate":57.14,"pickRate":7.41},{"key":"Alpha","winRate":56.46,"pickRate":11.11},{"key":"Ardan","winRate":48.59,"pickRate":29.55},{"key":"Baptiste","winRate":49.53,"pickRate":8.09},{"key":"Baron","winRate":51.6,"pickRate":18.9},{"key":"Blackfeather","winRate":56.28,"pickRate":13.83},{"key":"Catherine","winRate":49.15,"pickRate":22.15},{"key":"Celeste","winRate":48.31,"pickRate":20.18},{"key":"Flicker","winRate":35.71,"pickRate":6.35},{"key":"Fortress","winRate":48.21,"pickRate":14.74},{"key":"Glaive","winRate":55.26,"pickRate":11.49},{"key":"Grace","winRate":50.83,"pickRate":9.07},{"key":"Grumpjaw","winRate":53.33,"pickRate":6.8},{"key":"Gwen","winRate":51.69,"pickRate":20.18},{"key":"Idris","winRate":50.43,"pickRate":17.69},{"key":"Joule","winRate":48.25,"pickRate":8.62},{"key":"Kensei","winRate":43.44,"pickRate":9.22},{"key":"Kinetic","winRate":45.12,"pickRate":12.4},{"key":"Koshka","winRate":56.76,"pickRate":8.39},{"key":"Krul","winRate":46.76,"pickRate":10.51},{"key":"Lance","winRate":51.28,"pickRate":8.84},{"key":"Lyra","winRate":47.54,"pickRate":9.22},{"key":"Ozo","winRate":50.5,"pickRate":7.63},{"key":"Petal","winRate":38.46,"pickRate":2.95},{"key":"Phinn","winRate":47.97,"pickRate":9.3},{"key":"Reza","winRate":45.4,"pickRate":13.15},{"key":"Ringo","winRate":48.28,"pickRate":24.11},{"key":"Rona","winRate":47.27,"pickRate":8.31},{"key":"SAW","winRate":53.44,"pickRate":9.9},{"key":"Samuel","winRate":44.85,"pickRate":12.47},{"key":"Skaarf","winRate":48.53,"pickRate":20.56},{"key":"Skye","winRate":52.04,"pickRate":14.81},{"key":"Taka","winRate":51.67,"pickRate":9.07},{"key":"Tony","winRate":52.5,"pickRate":9.07},{"key":"Varya","winRate":49.47,"pickRate":14.21},{"key":"Vox","winRate":47.95,"pickRate":27.59},{"key":"Anka","winRate":50.67,"pickRate":5.67},{"key":"Churnwalker","winRate":53.85,"pickRate":3.93},{"key":"Kestrel","winRate":55.77,"pickRate":7.86},{"key":"Malene","winRate":45.16,"pickRate":7.03},{"key":"Lorelai","winRate":57.89,"pickRate":4.31},{"key":"Silvernail","winRate":38.64,"pickRate":3.33}],"playingWith":[{"key":"Adagio","winRate":46.34,"pickRate":6.2},{"key":"Alpha","winRate":53.19,"pickRate":3.55},{"key":"Anka","winRate":55.26,"pickRate":2.87},{"key":"Ardan","winRate":50.14,"pickRate":26.53},{"key":"Baron","winRate":48.33,"pickRate":15.8},{"key":"Blackfeather","winRate":47.48,"pickRate":10.51},{"key":"Catherine","winRate":51.91,"pickRate":17.76},{"key":"Celeste","winRate":50,"pickRate":16.02},{"key":"Flicker","winRate":59.3,"pickRate":6.5},{"key":"Fortress","winRate":55,"pickRate":9.07},{"key":"Glaive","winRate":53.85,"pickRate":6.88},{"key":"Grace","winRate":47.9,"pickRate":8.99},{"key":"Grumpjaw","winRate":48.89,"pickRate":3.4},{"key":"Gwen","winRate":48.42,"pickRate":23.89},{"key":"Idris","winRate":47.06,"pickRate":12.85},{"key":"Joule","winRate":39.34,"pickRate":4.61},{"key":"Kensei","winRate":61.82,"pickRate":4.16},{"key":"Kestrel","winRate":41.94,"pickRate":7.03},{"key":"Kinetic","winRate":53.68,"pickRate":14.36},{"key":"Koshka","winRate":40.48,"pickRate":3.17},{"key":"Krul","winRate":52.63,"pickRate":4.31},{"key":"Lance","winRate":43.82,"pickRate":6.73},{"key":"Lyra","winRate":53.91,"pickRate":8.69},{"key":"Malene","winRate":47.46,"pickRate":4.46},{"key":"Phinn","winRate":45.83,"pickRate":10.88},{"key":"Reza","winRate":49.46,"pickRate":7.03},{"key":"Ringo","winRate":52.41,"pickRate":28.27},{"key":"Rona","winRate":44.44,"pickRate":4.08},{"key":"SAW","winRate":47.89,"pickRate":10.73},{"key":"Samuel","winRate":42.62,"pickRate":9.22},{"key":"Silvernail","winRate":55.1,"pickRate":3.7},{"key":"Skaarf","winRate":56.13,"pickRate":16.02},{"key":"Skye","winRate":50,"pickRate":13.61},{"key":"Taka","winRate":36.36,"pickRate":4.16},{"key":"Varya","winRate":52.17,"pickRate":12.17},{"key":"Vox","winRate":50,"pickRate":27.21},{"key":"Churnwalker","winRate":47.62,"pickRate":4.76},{"key":"Ozo","winRate":45.83,"pickRate":3.63},{"key":"Petal","winRate":38.46,"pickRate":2.95},{"key":"Baptiste","winRate":33.82,"pickRate":5.14},{"key":"Tony","winRate":51.95,"pickRate":5.82},{"key":"Lorelai","winRate":60,"pickRate":2.27}],"categorySkills":[{"key":"acb","winRate":53.1,"pickRate":30.46},{"key":"abc","winRate":56.52,"pickRate":12.17}],"builds":[{"key":"DE,JB,AE,MJ","winRate":50.75,"pickRate":10.13,"variants":{"DE,JB,AE,MJ,BM":{"games":47,"wins":25},"DE,JB,AE,MJ,WT,BM":{"games":1,"wins":1},"DE,JB,AE,MJ":{"games":78,"wins":40},"DE,JB,AE,MJ,TS,BM,MJ":{"games":1,"wins":0},"DE,JB,AE,MJ,BM,AS,PW,TS":{"games":1,"wins":1},"DE,JB,AE,MJ,BM,FR,PW":{"games":1,"wins":0},"DE,JB,AE,MJ,BM,SH":{"games":1,"wins":0},"DE,JB,AE,MJ,BM,SH,AC":{"games":1,"wins":0},"DE,JB,AE,MJ,BM,TS":{"games":1,"wins":0},"DE,JB,AE,MJ,BM,TS,JB,BM":{"games":1,"wins":0},"DE,JB,AE,MJ,BM,PW":{"games":1,"wins":1}},"items":["Dragon's Eye","Journey Boots","Aegis","Metal Jacket"]},{"key":"DE,CW,AE,JB","winRate":71.43,"pickRate":2.12,"variants":{"DE,CW,AE,JB":{"games":14,"wins":11},"DE,CW,AE,JB,MJ":{"games":11,"wins":7},"DE,CW,AE,JB,AP":{"games":2,"wins":1},"DE,CW,AE,JB,SH":{"games":1,"wins":1}},"items":["Dragon's Eye","Clockwork","Aegis","Journey Boots"]},{"key":"DE,**,*,BM","winRate":50,"pickRate":1.21,"variants":{"DE,JB,MJ,BM":{"games":2,"wins":1},"DE,JB,MJ,BM,FR":{"games":1,"wins":1},"DE,JB,AE,BM":{"games":3,"wins":1},"DE,JB,AE,BM,MJ":{"games":4,"wins":2},"DE,JB,AE,BM,FR":{"games":1,"wins":1},"DE,JB,AE,BM,TS,JB,MJ":{"games":1,"wins":0},"DE,HC,SH,BM,CP":{"games":1,"wins":1},"DE,JB,SH,BM,FB":{"games":2,"wins":0},"DE,JB,SH,BM":{"games":1,"wins":1}},"items":["Dragon's Eye","Situational Boots","Situational Defense","Broken Myth"]}],"skills":[{"key":"a,b,a,a,b,c,a,a,c,b,b,c","category":"acb","winRate":53.1,"pickRate":30.46},{"key":"a,b,a,a,b,c,a,a,b,b,b,c","category":"abc","winRate":56.52,"pickRate":12.17}]}