{"name":"Silvernail","winRate":52.19,"pickRate":17.25,"banRate":0.63,"stats":[{"name":"goldPerMin","stats":609.8,"rank":2,"total":46},{"name":"killsPerGame","stats":4.67,"rank":17,"total":46},{"name":"deathsPerGame","stats":4.05,"rank":14,"total":46},{"name":"assistsPerGame","stats":5.1,"rank":35,"total":46},{"name":"farmPerGame","stats":104.98,"rank":3,"total":46},{"name":"damagePerGame","stats":52237.59,"rank":10,"total":46},{"name":"healingPerGame","stats":8932.73,"rank":35,"total":46},{"name":"kda","stats":2.41,"rank":21,"total":46}],"roles":[{"key":"Carry","winRate":51.89,"pickRate":91.95},{"key":"Jungler","winRate":58.19,"pickRate":7.09},{"key":"Captain","winRate":35.9,"pickRate":0.96}],"durations":[{"key":"10","winRate":52.03,"pickRate":3.66},{"key":"20","winRate":52.05,"pickRate":37.29},{"key":"30","winRate":52.27,"pickRate":53.2},{"key":"40","winRate":52.99,"pickRate":5.78},{"key":"50","winRate":33.33,"pickRate":0.07}],"playingAgainst":[{"key":"Adagio","winRate":51.91,"pickRate":13.61},{"key":"Alpha","winRate":57.32,"pickRate":4.05},{"key":"Anka","winRate":46.27,"pickRate":8.27},{"key":"Ardan","winRate":53.95,"pickRate":34.7},{"key":"Baptiste","winRate":49.55,"pickRate":8.27},{"key":"Baron","winRate":59.55,"pickRate":4.4},{"key":"Blackfeather","winRate":55.59,"pickRate":15.68},{"key":"Catherine","winRate":57.85,"pickRate":8.97},{"key":"Celeste","winRate":48.6,"pickRate":22.01},{"key":"Churnwalker","winRate":56.07,"pickRate":5.29},{"key":"Flicker","winRate":52.32,"pickRate":11.19},{"key":"Fortress","winRate":46.23,"pickRate":2.62},{"key":"Glaive","winRate":52.65,"pickRate":13.04},{"key":"Grace","winRate":50.79,"pickRate":9.39},{"key":"Grumpjaw","winRate":53.61,"pickRate":6.5},{"key":"Gwen","winRate":50.85,"pickRate":21.86},{"key":"Idris","winRate":52.45,"pickRate":19.17},{"key":"Inara","winRate":53.67,"pickRate":5.38},{"key":"Joule","winRate":51.93,"pickRate":5.75},{"key":"Kensei","winRate":64.02,"pickRate":4.05},{"key":"Kestrel","winRate":57.04,"pickRate":3.51},{"key":"Kinetic","winRate":51.27,"pickRate":27.17},{"key":"Koshka","winRate":53.09,"pickRate":6},{"key":"Krul","winRate":56.16,"pickRate":5.01},{"key":"Lance","winRate":53.24,"pickRate":12.94},{"key":"Lorelai","winRate":47.59,"pickRate":14.32},{"key":"Lyra","winRate":48.75,"pickRate":10.89},{"key":"Magnus","winRate":57.42,"pickRate":11.66},{"key":"Malene","winRate":60.52,"pickRate":6.69},{"key":"Ozo","winRate":59.14,"pickRate":2.3},{"key":"Petal","winRate":61.54,"pickRate":1.61},{"key":"Phinn","winRate":47.61,"pickRate":19.09},{"key":"Reim","winRate":59.66,"pickRate":2.94},{"key":"Reza","winRate":51.95,"pickRate":19.59},{"key":"Ringo","winRate":52.31,"pickRate":25.12},{"key":"Rona","winRate":56.59,"pickRate":3.19},{"key":"SAW","winRate":56.77,"pickRate":4.74},{"key":"Samuel","winRate":46.9,"pickRate":8.37},{"key":"Skaarf","winRate":44.51,"pickRate":16.87},{"key":"Skye","winRate":53.86,"pickRate":10.22},{"key":"Taka","winRate":61.39,"pickRate":2.49},{"key":"Varya","winRate":50.8,"pickRate":13.86},{"key":"Vox","winRate":51.46,"pickRate":31.24},{"key":"Yates","winRate":50.68,"pickRate":12.77},{"key":"Tony","winRate":66.41,"pickRate":3.24}],"playingWith":[{"key":"Adagio","winRate":52.47,"pickRate":12.99},{"key":"Alpha","winRate":46.9,"pickRate":3.58},{"key":"Anka","winRate":52.25,"pickRate":8.22},{"key":"Ardan","winRate":52.61,"pickRate":33.09},{"key":"Baptiste","winRate":56.9,"pickRate":7.34},{"key":"Baron","winRate":38.64,"pickRate":3.26},{"key":"Blackfeather","winRate":49.47,"pickRate":11.73},{"key":"Catherine","winRate":48.26,"pickRate":7.83},{"key":"Celeste","winRate":54.27,"pickRate":20.52},{"key":"Flicker","winRate":54.8,"pickRate":9.78},{"key":"Fortress","winRate":51.58,"pickRate":2.35},{"key":"Glaive","winRate":49.57,"pickRate":11.61},{"key":"Grace","winRate":54.99,"pickRate":9.16},{"key":"Grumpjaw","winRate":51.49,"pickRate":4.99},{"key":"Gwen","winRate":49.57,"pickRate":5.78},{"key":"Idris","winRate":49.71,"pickRate":12.87},{"key":"Inara","winRate":47.92,"pickRate":3.56},{"key":"Joule","winRate":45.49,"pickRate":5.75},{"key":"Kensei","winRate":41.27,"pickRate":3.11},{"key":"Kinetic","winRate":50.57,"pickRate":4.35},{"key":"Koshka","winRate":55.79,"pickRate":7.04},{"key":"Krul","winRate":51.18,"pickRate":4.2},{"key":"Lance","winRate":50,"pickRate":12.89},{"key":"Lorelai","winRate":59.08,"pickRate":13.46},{"key":"Lyra","winRate":52.33,"pickRate":10.62},{"key":"Magnus","winRate":53.72,"pickRate":10.94},{"key":"Malene","winRate":48.15,"pickRate":6},{"key":"Ozo","winRate":48.04,"pickRate":2.52},{"key":"Phinn","winRate":52.72,"pickRate":21.36},{"key":"Reim","winRate":50.41,"pickRate":3.04},{"key":"Reza","winRate":50.79,"pickRate":17.21},{"key":"Ringo","winRate":47.06,"pickRate":7.98},{"key":"Rona","winRate":43.3,"pickRate":2.4},{"key":"SAW","winRate":47.48,"pickRate":3.43},{"key":"Samuel","winRate":52.49,"pickRate":7.43},{"key":"Skaarf","winRate":58.69,"pickRate":19.61},{"key":"Skye","winRate":53.58,"pickRate":6.54},{"key":"Taka","winRate":50.53,"pickRate":2.35},{"key":"Varya","winRate":51.84,"pickRate":11.43},{"key":"Vox","winRate":53.32,"pickRate":23.81},{"key":"Yates","winRate":53.93,"pickRate":13.19},{"key":"Churnwalker","winRate":56.9,"pickRate":5.73},{"key":"Kestrel","winRate":40.26,"pickRate":1.9},{"key":"Petal","winRate":44.19,"pickRate":1.06},{"key":"Tony","winRate":55,"pickRate":1.98}],"categorySkills":[{"key":"bca","winRate":56.38,"pickRate":45.12},{"key":"bac","winRate":53.94,"pickRate":8.47},{"key":"acb","winRate":56.32,"pickRate":4.69}],"builds":[{"key":"SB,PS,BS,JB","winRate":58.82,"pickRate":3.36,"variants":{"SB,PS,BS,JB,BP,CB,SH":{"games":1,"wins":1},"SB,PS,BS,JB":{"games":46,"wins":29},"SB,PS,BS,JB,WM,AE,BP":{"games":6,"wins":1},"SB,PS,BS,JB,WM,AE":{"games":8,"wins":4},"SB,PS,BS,JB,WM,AE,TS":{"games":1,"wins":0},"SB,PS,BS,JB,AE":{"games":13,"wins":8},"SB,PS,BS,JB,BP,AE":{"games":10,"wins":6},"SB,PS,BS,JB,CS,BP":{"games":3,"wins":2},"SB,PS,BS,JB,WM":{"games":4,"wins":2},"SB,PS,BS,JB,TS":{"games":3,"wins":2},"SB,PS,BS,JB,SH,TB,SB":{"games":1,"wins":0},"SB,PS,BS,JB,BP":{"games":5,"wins":2},"SB,PS,BS,JB,CS,AE":{"games":2,"wins":2},"SB,PS,BS,JB,SH":{"games":9,"wins":7},"SB,PS,BS,JB,SM,AE":{"games":1,"wins":1},"SB,PS,BS,JB,BP,AE,SM":{"games":1,"wins":0},"SB,PS,BS,JB,CS,TT,TS":{"games":1,"wins":1},"SB,PS,BS,JB,WM,SH":{"games":1,"wins":1},"SB,PS,BS,JB,AE,BP":{"games":4,"wins":2},"SB,PS,BS,JB,AE,SH":{"games":2,"wins":2},"SB,PS,BS,JB,AE,BP,TS,JB":{"games":1,"wins":1},"SB,PS,BS,JB,AP,AP,AP,AP":{"games":1,"wins":0},"SB,PS,BS,JB,BS,AE,TT":{"games":1,"wins":0},"SB,PS,BS,JB,AP,BP,SH":{"games":1,"wins":0},"SB,PS,BS,JB,SH,BP":{"games":2,"wins":1},"SB,PS,BS,JB,CS":{"games":3,"wins":2},"SB,PS,BS,JB,TT,AE":{"games":1,"wins":0},"SB,PS,BS,JB,BP,SB":{"games":1,"wins":0},"SB,PS,BS,JB,BP,SH":{"games":1,"wins":1},"SB,PS,BS,JB,SH,TT":{"games":1,"wins":1},"SB,PS,BS,JB,TT,TS":{"games":1,"wins":1}},"items":["Sorrowblade","Poisoned Shiv","Bonesaw","Journey Boots"]},{"key":"SB,PS,JB,BS","winRate":77.78,"pickRate":2.89,"variants":{"SB,PS,JB,BS,AE":{"games":9,"wins":9},"SB,PS,JB,BS":{"games":48,"wins":38},"SB,PS,JB,BS,BP,AE":{"games":9,"wins":9},"SB,PS,JB,BS,BP":{"games":12,"wins":9},"SB,PS,JB,BS,WM,AE":{"games":8,"wins":7},"SB,PS,JB,BS,AE,TS":{"games":2,"wins":2},"SB,PS,JB,BS,BP,AE,TS":{"games":1,"wins":0},"SB,PS,JB,BS,CS,CB":{"games":1,"wins":1},"SB,PS,JB,BS,WM,AE,BP":{"games":4,"wins":3},"SB,PS,JB,BS,WM,AE,SH":{"games":1,"wins":0},"SB,PS,JB,BS,MJ":{"games":1,"wins":1},"SB,PS,JB,BS,WM":{"games":4,"wins":3},"SB,PS,JB,BS,AE,BP":{"games":1,"wins":1},"SB,PS,JB,BS,WM,AE,WM":{"games":1,"wins":0},"SB,PS,JB,BS,SH":{"games":2,"wins":2},"SB,PS,JB,BS,TT":{"games":2,"wins":1},"SB,PS,JB,BS,AE,BP,TS":{"games":1,"wins":0},"SB,PS,JB,BS,BP,AE,TS,JB":{"games":1,"wins":0},"SB,PS,JB,BS,CS":{"games":1,"wins":1},"SB,PS,JB,BS,TS,JB":{"games":1,"wins":1},"SB,PS,JB,BS,WM,AE,MJ":{"games":1,"wins":0},"SB,PS,JB,BS,TT,BP,SH,TS,JB":{"games":1,"wins":1},"SB,PS,JB,BS,BP,SH":{"games":1,"wins":0},"SB,PS,JB,BS,CS,AE":{"games":1,"wins":1},"SB,PS,JB,BS,TT,CB":{"games":1,"wins":0},"SB,PS,JB,BS,BP,AE,SS":{"games":1,"wins":0},"SB,PS,JB,BS,SS":{"games":1,"wins":1}},"items":["Sorrowblade","Poisoned Shiv","Journey Boots","Bonesaw"]},{"key":"SM,BP,BS,JB","winRate":65.77,"pickRate":2.74,"variants":{"SM,BP,BS,JB":{"games":46,"wins":32},"SM,BP,BS,JB,AE":{"games":11,"wins":7},"SM,BP,BS,JB,WM":{"games":8,"wins":5},"SM,BP,BS,JB,WM,AE":{"games":5,"wins":4},"SM,BP,BS,JB,AE,SL":{"games":1,"wins":1},"SM,BP,BS,JB,SL":{"games":2,"wins":2},"SM,BP,BS,JB,SB,SH":{"games":1,"wins":1},"SM,BP,BS,JB,CB":{"games":1,"wins":0},"SM,BP,BS,JB,CB,TT":{"games":1,"wins":0},"SM,BP,BS,JB,SB":{"games":2,"wins":2},"SM,BP,BS,JB,TT":{"games":5,"wins":2},"SM,BP,BS,JB,SH,AE":{"games":2,"wins":1},"SM,BP,BS,JB,TT,AE":{"games":3,"wins":2},"SM,BP,BS,JB,AE,MJ":{"games":1,"wins":1},"SM,BP,BS,JB,SB,AE":{"games":1,"wins":0},"SM,BP,BS,JB,SH":{"games":6,"wins":4},"SM,BP,BS,JB,TB":{"games":1,"wins":1},"SM,BP,BS,JB,WM,TT,AE":{"games":1,"wins":1},"SM,BP,BS,JB,AE,CS":{"games":1,"wins":0},"SM,BP,BS,JB,CS,AE":{"games":1,"wins":1},"SM,BP,BS,JB,WM,AE,TT":{"games":1,"wins":1},"SM,BP,BS,JB,WM,AE,SL":{"games":1,"wins":1},"SM,BP,BS,JB,TT,CB":{"games":1,"wins":1},"SM,BP,BS,JB,WM,AE,CS":{"games":1,"wins":0},"SM,BP,BS,JB,SH,SS":{"games":1,"wins":0},"SM,BP,BS,JB,CS":{"games":2,"wins":1},"SM,BP,BS,JB,MJ":{"games":1,"wins":0},"SM,BP,BS,JB,SH,TS":{"games":2,"wins":1},"SM,BP,BS,JB,CS,SH":{"games":1,"wins":1}},"items":["Serpent Mask","Breaking Point","Bonesaw","Journey Boots"]},{"key":"SM,BP,BS,*","winRate":55,"pickRate":2.47,"variants":{"SM,BP,BS,SH":{"games":14,"wins":6},"SM,BP,BS,SH,JB":{"games":11,"wins":4},"SM,BP,BS,SH,TS":{"games":3,"wins":2},"SM,BP,BS,SH,WT,CS":{"games":1,"wins":1},"SM,BP,BS,SH,TT":{"games":1,"wins":0},"SM,BP,BS,SH,WT":{"games":1,"wins":1},"SM,BP,BS,SH,HC":{"games":3,"wins":2},"SM,BP,BS,SH,HC,TT":{"games":1,"wins":0},"SM,BP,BS,SH,JB,TB":{"games":1,"wins":1},"SM,BP,BS,SH,JB,AE":{"games":1,"wins":0},"SM,BP,BS,SH,TT,JB":{"games":1,"wins":1},"SM,BP,BS,SH,JB,TT,SS":{"games":1,"wins":0},"SM,BP,BS,SH,JB,TT":{"games":1,"wins":1},"SM,BP,BS,SH,HC,AE":{"games":1,"wins":0},"SM,BP,BS,SH,JB,CB,AE":{"games":1,"wins":0},"SM,BP,BS,AE,JB,PS":{"games":1,"wins":0},"SM,BP,BS,AE,JB":{"games":3,"wins":2},"SM,BP,BS,AE":{"games":5,"wins":3},"SM,BP,BS,AE,HC":{"games":2,"wins":1},"SM,BP,BS,AE,SH,JB":{"games":2,"wins":1},"SM,BP,BS,AE,WM,HC,SH":{"games":1,"wins":1},"SM,BP,BS,WM,JB,AE":{"games":1,"wins":0},"SM,BP,BS,WM,AE":{"games":6,"wins":4},"SM,BP,BS,WM,SH":{"games":2,"wins":1},"SM,BP,BS,WM":{"games":9,"wins":4},"SM,BP,BS,WM,AE,BP":{"games":1,"wins":1},"SM,BP,BS,WM,JB":{"games":5,"wins":3},"SM,BP,BS,WM,AE,SH,JB":{"games":2,"wins":2},"SM,BP,BS,WM,AE,JB":{"games":3,"wins":2},"SM,BP,BS,WM,JB,TS":{"games":1,"wins":1},"SM,BP,BS,WM,HC":{"games":1,"wins":1},"SM,BP,BS,WM,SH,HC":{"games":1,"wins":1},"SM,BP,BS,WM,AE,SB,JB":{"games":1,"wins":1},"SM,BP,BS,WM,SH,SB":{"games":1,"wins":0},"SM,BP,BS,WM,JB,TT":{"games":1,"wins":0},"SM,BP,BS,MJ,JB":{"games":1,"wins":0},"SM,BP,BS,MJ,CS,JB":{"games":1,"wins":1},"SM,BP,BS,CS":{"games":2,"wins":2},"SM,BP,BS,CS,HC":{"games":1,"wins":1},"SM,BP,BS,CS,JB":{"games":3,"wins":2},"SM,BP,BS,CS,MJ":{"games":1,"wins":1}},"items":["Serpent Mask","Breaking Point","Bonesaw","Situational Defense"]},{"key":"SB,PS,BS,*","winRate":63.38,"pickRate":1.75,"variants":{"SB,PS,BS,CS,JB":{"games":2,"wins":1},"SB,PS,BS,CS,JB,TT,BP":{"games":1,"wins":1},"SB,PS,BS,CS,BP":{"games":1,"wins":0},"SB,PS,BS,CS,HC,BP":{"games":1,"wins":0},"SB,PS,BS,CS,WM,SH,HC,BP,TT":{"games":1,"wins":1},"SB,PS,BS,CS":{"games":2,"wins":2},"SB,PS,BS,CS,JB,MJ,TS":{"games":1,"wins":1},"SB,PS,BS,MJ,JB,BP":{"games":1,"wins":1},"SB,PS,BS,AE":{"games":4,"wins":3},"SB,PS,BS,AE,BP,JB":{"games":1,"wins":0},"SB,PS,BS,AE,JB":{"games":3,"wins":2},"SB,PS,BS,AE,BP,HC":{"games":1,"wins":1},"SB,PS,BS,WM,AE,TS":{"games":1,"wins":1},"SB,PS,BS,WM,AE":{"games":11,"wins":5},"SB,PS,BS,WM,AE,JB":{"games":6,"wins":6},"SB,PS,BS,WM":{"games":5,"wins":3},"SB,PS,BS,WM,SH":{"games":2,"wins":2},"SB,PS,BS,WM,HC,AE,BP":{"games":1,"wins":1},"SB,PS,BS,WM,JB,AE":{"games":1,"wins":1},"SB,PS,BS,WM,JB,AE,BP":{"games":1,"wins":1},"SB,PS,BS,WM,AE,TT,WT":{"games":1,"wins":0},"SB,PS,BS,WM,AE,JB,BP":{"games":4,"wins":3},"SB,PS,BS,WM,CS,AE":{"games":1,"wins":0},"SB,PS,BS,WM,AE,JB,TS":{"games":1,"wins":1},"SB,PS,BS,SH":{"games":8,"wins":3},"SB,PS,BS,SH,JB,BP":{"games":2,"wins":0},"SB,PS,BS,SH,HC":{"games":1,"wins":1},"SB,PS,BS,SH,BP,JB":{"games":1,"wins":1},"SB,PS,BS,SH,JB,TT":{"games":1,"wins":1},"SB,PS,BS,SH,JB":{"games":1,"wins":0},"SB,PS,BS,SH,BP,WT,HC,JB":{"games":1,"wins":1},"SB,PS,BS,SH,JB,TS":{"games":2,"wins":1}},"items":["Sorrowblade","Poisoned Shiv","Bonesaw","Situational Defense"]},{"key":"SM,BP,JB,BS","winRate":64.29,"pickRate":1.73,"variants":{"SM,BP,JB,BS":{"games":23,"wins":13},"SM,BP,JB,BS,SH":{"games":4,"wins":4},"SM,BP,JB,BS,SB":{"games":1,"wins":1},"SM,BP,JB,BS,CS,AE":{"games":1,"wins":1},"SM,BP,JB,BS,SH,AE":{"games":3,"wins":2},"SM,BP,JB,BS,AE,SH":{"games":1,"wins":1},"SM,BP,JB,BS,WM,AE,AP":{"games":1,"wins":0},"SM,BP,JB,BS,WM,AE":{"games":8,"wins":4},"SM,BP,JB,BS,AE":{"games":8,"wins":6},"SM,BP,JB,BS,MJ,CS":{"games":1,"wins":0},"SM,BP,JB,BS,WM,SH,AE":{"games":1,"wins":1},"SM,BP,JB,BS,SS,AE":{"games":1,"wins":1},"SM,BP,JB,BS,TT":{"games":2,"wins":1},"SM,BP,JB,BS,TT,AE":{"games":1,"wins":1},"SM,BP,JB,BS,WM,AE,SH":{"games":1,"wins":0},"SM,BP,JB,BS,AE,TT":{"games":1,"wins":1},"SM,BP,JB,BS,SB,CS":{"games":1,"wins":0},"SM,BP,JB,BS,SH,SS":{"games":1,"wins":1},"SM,BP,JB,BS,WM":{"games":3,"wins":2},"SM,BP,JB,BS,WM,SH":{"games":1,"wins":0},"SM,BP,JB,BS,TT,AE,TS,JB":{"games":1,"wins":1},"SM,BP,JB,BS,CS,PS,TS":{"games":1,"wins":1},"SM,BP,JB,BS,SS,SH":{"games":2,"wins":2},"SM,BP,JB,BS,SH,TT":{"games":1,"wins":1},"SM,BP,JB,BS,AE,SL":{"games":1,"wins":0}},"items":["Serpent Mask","Breaking Point","Journey Boots","Bonesaw"]},{"key":"SB,PS,BP,JB","winRate":60,"pickRate":1.36,"variants":{"SB,PS,BP,JB,CS":{"games":1,"wins":0},"SB,PS,BP,JB,MJ,BS":{"games":1,"wins":1},"SB,PS,BP,JB,TT,BS":{"games":1,"wins":1},"SB,PS,BP,JB":{"games":15,"wins":9},"SB,PS,BP,JB,AE":{"games":7,"wins":3},"SB,PS,BP,JB,BS,AE":{"games":2,"wins":2},"SB,PS,BP,JB,SH":{"games":6,"wins":3},"SB,PS,BP,JB,BS,CS":{"games":1,"wins":1},"SB,PS,BP,JB,BS,AE,SM":{"games":1,"wins":0},"SB,PS,BP,JB,AE,BS":{"games":3,"wins":1},"SB,PS,BP,JB,BS":{"games":2,"wins":1},"SB,PS,BP,JB,BS,SH":{"games":1,"wins":1},"SB,PS,BP,JB,CS,BS":{"games":1,"wins":1},"SB,PS,BP,JB,WM":{"games":2,"wins":0},"SB,PS,BP,JB,CB":{"games":1,"wins":1},"SB,PS,BP,JB,TT,AE":{"games":1,"wins":1},"SB,PS,BP,JB,WM,AE":{"games":3,"wins":2},"SB,PS,BP,JB,TT":{"games":1,"wins":1},"SB,PS,BP,JB,BS,SL":{"games":1,"wins":1},"SB,PS,BP,JB,BS,AE,TS":{"games":1,"wins":0},"SB,PS,BP,JB,TS":{"games":1,"wins":1},"SB,PS,BP,JB,AE,TT":{"games":1,"wins":1},"SB,PS,BP,JB,TS,JB,AE,TS,JB":{"games":1,"wins":1}},"items":["Sorrowblade","Poisoned Shiv","Breaking Point","Journey Boots"]},{"key":"SB,PS,BP,*","winRate":48.57,"pickRate":0.86,"variants":{"SB,PS,BP,WM,AE,HC":{"games":1,"wins":0},"SB,PS,BP,WM,JB":{"games":1,"wins":1},"SB,PS,BP,WM,AE":{"games":2,"wins":1},"SB,PS,BP,WM":{"games":2,"wins":0},"SB,PS,BP,WM,AE,JB":{"games":5,"wins":2},"SB,PS,BP,WM,JB,AE,BS":{"games":1,"wins":1},"SB,PS,BP,WM,AE,BS":{"games":2,"wins":1},"SB,PS,BP,WM,JB,TB,SH":{"games":1,"wins":0},"SB,PS,BP,WM,AE,TT":{"games":1,"wins":0},"SB,PS,BP,AE":{"games":5,"wins":2},"SB,PS,BP,AE,HC":{"games":1,"wins":1},"SB,PS,BP,AE,BS,JB":{"games":1,"wins":1},"SB,PS,BP,SH":{"games":2,"wins":1},"SB,PS,BP,SH,BS":{"games":1,"wins":0},"SB,PS,BP,SH,JB":{"games":3,"wins":2},"SB,PS,BP,SH,JB,SM":{"games":1,"wins":1},"SB,PS,BP,SH,JB,BS":{"games":2,"wins":2},"SB,PS,BP,MJ":{"games":2,"wins":1},"SB,PS,BP,CS,JB":{"games":1,"wins":0}},"items":["Sorrowblade","Poisoned Shiv","Breaking Point","Situational Defense"]},{"key":"SB,PS,JB,BP","winRate":61.29,"pickRate":0.77,"variants":{"SB,PS,JB,BP,SH":{"games":1,"wins":0},"SB,PS,JB,BP":{"games":10,"wins":4},"SB,PS,JB,BP,AE":{"games":4,"wins":2},"SB,PS,JB,BP,BS,AE":{"games":1,"wins":1},"SB,PS,JB,BP,CS,WM,AE":{"games":1,"wins":1},"SB,PS,JB,BP,CB":{"games":1,"wins":1},"SB,PS,JB,BP,BS":{"games":5,"wins":3},"SB,PS,JB,BP,WM,AE,BS":{"games":1,"wins":1},"SB,PS,JB,BP,AE,BS":{"games":2,"wins":2},"SB,PS,JB,BP,BS,CS":{"games":1,"wins":1},"SB,PS,JB,BP,WM,AE":{"games":1,"wins":1},"SB,PS,JB,BP,AE,BS,SS,SM":{"games":1,"wins":0},"SB,PS,JB,BP,AE,TT":{"games":1,"wins":1},"SB,PS,JB,BP,BS,MJ,TS":{"games":1,"wins":1}},"items":["Sorrowblade","Poisoned Shiv","Journey Boots","Breaking Point"]},{"key":"SM,BS,BP,JB","winRate":52,"pickRate":0.62,"variants":{"SM,BS,BP,JB,CS,AE":{"games":1,"wins":1},"SM,BS,BP,JB,WM":{"games":1,"wins":0},"SM,BS,BP,JB,AE":{"games":2,"wins":1},"SM,BS,BP,JB":{"games":11,"wins":5},"SM,BS,BP,JB,SH":{"games":2,"wins":1},"SM,BS,BP,JB,CB,SH":{"games":1,"wins":0},"SM,BS,BP,JB,TT":{"games":3,"wins":3},"SM,BS,BP,JB,AE,TT":{"games":1,"wins":0},"SM,BS,BP,JB,TT,AE,PS":{"games":1,"wins":1},"SM,BS,BP,JB,WM,SH":{"games":1,"wins":0},"SM,BS,BP,JB,MJ,AE":{"games":1,"wins":1}},"items":["Serpent Mask","Bonesaw","Breaking Point","Journey Boots"]},{"key":"SM,BP,*,BS","winRate":45.83,"pickRate":0.59,"variants":{"SM,BP,SH,BS":{"games":3,"wins":0},"SM,BP,SH,BS,HC,PS":{"games":1,"wins":1},"SM,BP,SH,BS,HC,SS,TT":{"games":1,"wins":1},"SM,BP,SH,BS,HC":{"games":1,"wins":1},"SM,BP,SH,BS,JB":{"games":2,"wins":1},"SM,BP,SH,BS,JB,MJ":{"games":1,"wins":1},"SM,BP,SH,BS,WT":{"games":1,"wins":1},"SM,BP,SH,BS,SB":{"games":1,"wins":1},"SM,BP,SH,BS,WT,TT":{"games":1,"wins":0},"SM,BP,WM,BS,SH,JB":{"games":1,"wins":1},"SM,BP,WM,BS,JB":{"games":1,"wins":1},"SM,BP,WM,BS":{"games":3,"wins":0},"SM,BP,WM,BS,SL,WT":{"games":1,"wins":0},"SM,BP,AE,BS,JB,TT":{"games":1,"wins":0},"SM,BP,AE,BS,JB":{"games":1,"wins":0},"SM,BP,AE,BS":{"games":1,"wins":0},"SM,BP,CS,BS,JB,SB":{"games":1,"wins":1},"SM,BP,CS,BS,JB":{"games":1,"wins":1},"SM,BP,CS,BS,SS":{"games":1,"wins":0}},"items":["Serpent Mask","Breaking Point","Situational Defense","Bonesaw"]},{"key":"SS,BP,SH,BS","winRate":54.55,"pickRate":0.54,"variants":{"SS,BP,SH,BS":{"games":9,"wins":4},"SS,BP,SH,BS,JB":{"games":10,"wins":6},"SS,BP,SH,BS,PS":{"games":2,"wins":2},"SS,BP,SH,BS,JB,TS":{"games":1,"wins":0}},"items":["Spellsword","Breaking Point","Slumbering Husk","Bonesaw"]},{"key":"SB,JB,PS,BS","winRate":75,"pickRate":0.49,"variants":{"SB,JB,PS,BS,AE":{"games":2,"wins":1},"SB,JB,PS,BS,BP":{"games":3,"wins":2},"SB,JB,PS,BS":{"games":3,"wins":2},"SB,JB,PS,BS,BP,AE,TS":{"games":1,"wins":1},"SB,JB,PS,BS,BP,AE":{"games":3,"wins":3},"SB,JB,PS,BS,WM":{"games":2,"wins":2},"SB,JB,PS,BS,WM,AE":{"games":2,"wins":1},"SB,JB,PS,BS,AE,TT":{"games":1,"wins":0},"SB,JB,PS,BS,AE,BP":{"games":1,"wins":1},"SB,JB,PS,BS,BP,SH":{"games":1,"wins":1},"SB,JB,PS,BS,SH":{"games":1,"wins":1}},"items":["Sorrowblade","Journey Boots","Poisoned Shiv","Bonesaw"]},{"key":"SB,PS,BP,BS","winRate":77.78,"pickRate":0.44,"variants":{"SB,PS,BP,BS,HC,SH,CW,CW":{"games":1,"wins":0},"SB,PS,BP,BS,WM,JB,AE":{"games":1,"wins":0},"SB,PS,BP,BS":{"games":9,"wins":8},"SB,PS,BP,BS,JB,AE":{"games":2,"wins":1},"SB,PS,BP,BS,CS":{"games":1,"wins":1},"SB,PS,BP,BS,WT,JB,AE":{"games":1,"wins":1},"SB,PS,BP,BS,WM,AE,JB":{"games":1,"wins":1},"SB,PS,BP,BS,CS,JB":{"games":1,"wins":1},"SB,PS,BP,BS,HC":{"games":1,"wins":1}},"items":["Sorrowblade","Poisoned Shiv","Breaking Point","Bonesaw"]},{"key":"SB,PS,BS,BP","winRate":66.67,"pickRate":0.44,"variants":{"SB,PS,BS,BP,JB":{"games":4,"wins":2},"SB,PS,BS,BP,AE,JB":{"games":1,"wins":1},"SB,PS,BS,BP,AE,HC":{"games":1,"wins":1},"SB,PS,BS,BP":{"games":3,"wins":2},"SB,PS,BS,BP,AE,JB,CS,CS,CS,CS":{"games":1,"wins":0},"SB,PS,BS,BP,AE,JB,TS":{"games":1,"wins":1},"SB,PS,BS,BP,JB,AE":{"games":1,"wins":1},"SB,PS,BS,BP,AE":{"games":2,"wins":2},"SB,PS,BS,BP,JB,CB":{"games":1,"wins":0},"SB,PS,BS,BP,JB,SH":{"games":1,"wins":1},"SB,PS,BS,BP,TS,TT":{"games":1,"wins":0},"SB,PS,BS,BP,CB":{"games":1,"wins":1}},"items":["Sorrowblade","Poisoned Shiv","Bonesaw","Breaking Point"]}],"skills":[{"key":"b,a,b,b,a,c,b,b,c,a,a,c","category":"bca","winRate":56.95,"pickRate":38.03},{"key":"b,a,b,b,a,c,b,b,a,a,a,c","category":"bac","winRate":57.35,"pickRate":5.21},{"key":"b,b,a,b,a,c,b,b,c,a,a,c","category":"bca","winRate":55.48,"pickRate":3.83},{"key":"a,b,a,a,b,c,a,a,c,b,b,c","category":"acb","winRate":56.82,"pickRate":3.26},{"key":"b,a,b,b,a,c,b,b,c,a,a,a","category":"bac","winRate":48.48,"pickRate":3.26},{"key":"a,b,b,b,a,c,b,b,c,a,a,c","category":"bca","winRate":41.33,"pickRate":1.85},{"key":"b,a,a,a,b,c,a,a,c,b,b,c","category":"acb","winRate":55.17,"pickRate":1.43},{"key":"b,a,b,b,a,c,b,b,a,c,a,c","category":"bca","winRate":63.16,"pickRate":1.41}]}